{
  "shop": {
    "motorcycle": [
      {
        "displayName": "Harley-Davidson",
        "id": "harleydavidson-da9cac",
        "locationSet": {"include": ["001"]},
        "nomatch": [
          "shop/motorcycle_repair|Harley-Davidson"
        ],
        "oldid": "shop/motorcycle|Harley-Davidson",
        "tags": {
          "brand": "Harley-Davidson",
          "brand:wikidata": "Q192814",
          "brand:wikipedia": "en:Harley-Davidson",
          "name": "Harley-Davidson",
          "shop": "motorcycle"
        }
      },
      {
        "displayName": "Honda",
        "id": "honda-da9cac",
        "locationSet": {"include": ["001"]},
        "nomatch": ["shop/car|Honda"],
        "oldid": "shop/motorcycle|Honda",
        "tags": {
          "brand": "Honda",
          "brand:wikidata": "Q9584",
          "brand:wikipedia": "en:Honda",
          "name": "Honda",
          "shop": "motorcycle"
        }
      },
      {
        "displayName": "KTM",
        "id": "ktm-da9cac",
        "locationSet": {"include": ["001"]},
        "nomatch": ["shop/motorcycle_repair|KTM"],
        "oldid": "shop/motorcycle|KTM",
        "tags": {
          "brand": "KTM",
          "brand:wikidata": "Q215657",
          "brand:wikipedia": "en:KTM",
          "name": "KTM",
          "shop": "motorcycle"
        }
      },
      {
        "displayName": "Kawasaki",
        "id": "kawasaki-da9cac",
        "locationSet": {"include": ["001"]},
        "oldid": "shop/motorcycle|Kawasaki",
        "tags": {
          "brand": "Kawasaki",
          "brand:wikidata": "Q6379855",
          "brand:wikipedia": "en:Kawasaki motorcycles",
          "name": "Kawasaki",
          "shop": "motorcycle"
        }
      },
      {
        "displayName": "Motortrade",
        "id": "motortrade-0e4718",
        "locationSet": {"include": ["ph"]},
        "oldid": "shop/motorcycle|Motortrade",
        "tags": {
          "brand": "Motortrade",
          "brand:wikidata": "Q48803162",
          "brand:wikipedia": "en:Motortrade",
          "name": "Motortrade",
          "shop": "motorcycle"
        }
      },
      {
        "displayName": "Suzuki",
        "id": "suzuki-da9cac",
        "locationSet": {"include": ["001"]},
        "nomatch": ["shop/car|Suzuki"],
        "oldid": "shop/motorcycle|Suzuki",
        "tags": {
          "brand": "Suzuki",
          "brand:wikidata": "Q181642",
          "brand:wikipedia": "en:Suzuki",
          "name": "Suzuki",
          "shop": "motorcycle"
        }
      },
      {
        "displayName": "Yamaha",
        "id": "yamaha-da9cac",
        "locationSet": {"include": ["001"]},
        "oldid": "shop/motorcycle|Yamaha",
        "tags": {
          "brand": "Yamaha",
          "brand:wikidata": "Q158888",
          "brand:wikipedia": "en:Yamaha Motor Company",
          "name": "Yamaha",
          "shop": "motorcycle"
        }
      },
      {
        "displayName": "バイク王",
        "id": "バイク王-7fa346",
        "locationSet": {"include": ["jp"]},
        "oldid": "shop/motorcycle|バイク王",
        "tags": {
          "brand": "バイク王",
          "brand:en": "Bike O",
          "brand:ja": "バイク王",
          "brand:wikidata": "Q11327447",
          "brand:wikipedia": "ja:バイク王&カンパニー",
          "name": "バイク王",
          "name:en": "Bike O",
          "name:ja": "バイク王",
          "shop": "motorcycle"
        }
      },
      {
        "displayName": "レッドバロン",
        "id": "レッドバロン-7fa346",
        "locationSet": {"include": ["jp"]},
        "oldid": "shop/motorcycle|レッドバロン",
        "tags": {
          "brand": "レッドバロン",
          "brand:en": "Red Baron",
          "brand:ja": "レッドバロン",
          "brand:wikidata": "Q11349759",
          "brand:wikipedia": "ja:レッドバロン (企業)",
          "name": "レッドバロン",
          "name:en": "Red Baron",
          "name:ja": "レッドバロン",
          "shop": "motorcycle"
        }
      }
    ]
  }
}