{
  "shop/musical_instrument|Guitar Center": {
    "countryCodes": ["us"],
    "tags": {
      "brand": "Guitar Center",
      "brand:wikidata": "Q3622794",
      "brand:wikipedia": "en:Guitar Center",
      "name": "Guitar Center",
      "shop": "musical_instrument"
    }
  },
  "shop/musical_instrument|Long & McQuade": {
    "countryCodes": ["ca"],
    "tags": {
      "brand": "Long & McQuade",
      "brand:wikidata": "Q6672180",
      "brand:wikipedia": "en:Long & McQuade",
      "name": "Long & McQuade",
      "shop": "musical_instrument"
    }
  },
  "shop/musical_instrument|山野楽器": {
    "countryCodes": ["jp"],
    "tags": {
      "brand": "山野楽器",
      "brand:en": "Yamano Music",
      "brand:ja": "山野楽器",
      "brand:wikidata": "Q11471074",
      "brand:wikipedia": "ja:山野楽器",
      "name": "山野楽器",
      "name:en": "Yamano Music",
      "name:ja": "山野楽器",
      "shop": "musical_instrument"
    }
  },
  "shop/musical_instrument|島村楽器": {
    "countryCodes": ["jp"],
    "tags": {
      "brand": "島村楽器",
      "brand:en": "Shimamura Music",
      "brand:ja": "島村楽器",
      "brand:wikidata": "Q11476395",
      "brand:wikipedia": "ja:島村楽器",
      "name": "島村楽器",
      "name:en": "Shimamura Music",
      "name:ja": "島村楽器",
      "shop": "musical_instrument"
    }
  }
}