{
  "properties": {
    "path": "brands/amenity/atm",
    "skipCollection": true,
    "preserveTags": ["^name"],
    "exclude": {"generic": ["^atm$"]}
  },
  "items": [
    {
      "note": "Auto create ATMs for all banks (remove names per #7236)",
      "templateExclude": ["monobank"],
      "templateSource": "brands/amenity/bank",
      "templateTags": {
        "amenity": "atm",
        "name": "",
        "operator": "{source.tags.brand}",
        "operator:wikidata": "{source.tags.brand:wikidata}"
      }
    },
    {
      "displayName": "Allpoint",
      "id": "allpoint-a81297",
      "locationSet": {
        "include": ["au", "ca", "gb", "mx", "us"]
      },
      "tags": {
        "amenity": "atm",
        "brand": "Allpoint",
        "brand:wikidata": "Q4733264"
      }
    },
    {
      "displayName": "American Crypto ATM",
      "id": "americancryptoatm-93d3a2",
      "locationSet": {"include": ["us"]},
      "matchTags": ["amenity/bank"],
      "tags": {
        "amenity": "atm",
        "brand": "American Crypto ATM"
      }
    },
    {
      "displayName": "atmx by Armaguard",
      "id": "armaguard-8509c1",
      "locationSet": {"include": ["au"]},
      "tags": {
        "amenity": "atm",
        "brand": "Armaguard",
        "brand:wikidata": "Q118898974"
      }
    },
    {
      "displayName": "Auro Domus",
      "id": "aurodomus-4d8c03",
      "locationSet": {"include": ["hr"]},
      "tags": {
        "amenity": "atm",
        "brand": "Auro Domus",
        "brand:wikidata": "Q125811872",
        "operator": "Auro Domus",
        "operator:wikidata": "Q125811872"
      }
    },
    {
      "displayName": "Banco24Horas",
      "id": "banco24horas-a02d2b",
      "locationSet": {"include": ["br"]},
      "matchNames": ["branco24horas"],
      "tags": {
        "amenity": "atm",
        "brand": "Banco24Horas",
        "brand:wikidata": "Q4854069"
      }
    },
    {
      "displayName": "Bancontact CASH",
      "id": "bancontactcash-8a4913",
      "locationSet": {"include": ["bel"]},
      "tags": {
        "amenity": "atm",
        "brand": "Bancontact CASH",
        "brand:wikidata": "Q112875867",
        "operator": "Batopin",
        "operator:wikidata": "Q97142699"
      }
    },
    {
      "displayName": "Bitcoin Depot",
      "id": "bitcoindepot-93d3a2",
      "locationSet": {"include": ["us"]},
      "matchTags": ["amenity/bank"],
      "tags": {
        "amenity": "atm",
        "brand": "Bitcoin Depot",
        "brand:wikidata": "Q109824499",
        "currency:XBT": "yes"
      }
    },
    {
      "displayName": "Cardtronics",
      "id": "cardtronics-244dba",
      "locationSet": {
        "include": [
          "au",
          "ca",
          "de",
          "es",
          "ie",
          "mx",
          "nz",
          "us",
          "za"
        ]
      },
      "tags": {
        "amenity": "atm",
        "brand": "Cardtronics",
        "brand:wikidata": "Q50239180"
      }
    },
    {
      "displayName": "Cashzone",
      "id": "cashzone-396707",
      "locationSet": {"include": ["gb"]},
      "matchNames": [
        "cardtronics",
        "cardtronics uk ltd",
        "cashzone ltd"
      ],
      "tags": {
        "amenity": "atm",
        "brand": "Cashzone",
        "brand:wikidata": "Q110738461",
        "network": "Allpoint",
        "network:wikidata": "Q4733264"
      }
    },
    {
      "displayName": "Chime",
      "id": "chime-93d3a2",
      "locationSet": {"include": ["us"]},
      "tags": {
        "amenity": "atm",
        "brand": "Chime",
        "brand:wikidata": "Q85752013"
      }
    },
    {
      "displayName": "China UnionPay",
      "id": "chinaunionpay-7886cb",
      "locationSet": {"include": ["cn"]},
      "tags": {
        "amenity": "atm",
        "brand": "China UnionPay",
        "brand:wikidata": "Q719625"
      }
    },
    {
      "displayName": "CO-OP Financial Services",
      "id": "coopfinancialservices-93d3a2",
      "locationSet": {"include": ["us"]},
      "matchNames": ["cu cooperative systems"],
      "tags": {
        "amenity": "atm",
        "brand": "CO-OP Financial Services",
        "brand:wikidata": "Q5013238"
      }
    },
    {
      "displayName": "CoinFlip",
      "id": "coinflip-93d3a2",
      "locationSet": {"include": ["us"]},
      "tags": {
        "amenity": "atm",
        "brand": "CoinFlip",
        "brand:wikidata": "Q109850256",
        "currency:XBT": "yes"
      }
    },
    {
      "displayName": "Coinhub",
      "id": "coinhub-93d3a2",
      "locationSet": {"include": ["us"]},
      "tags": {
        "amenity": "atm",
        "brand": "Coinhub",
        "brand:wikidata": "Q126195855",
        "currency:XBT": "yes",
        "name": "Coinhub"
      }
    },
    {
      "displayName": "Coinsource",
      "id": "coinsource-93d3a2",
      "locationSet": {"include": ["us"]},
      "tags": {
        "amenity": "atm",
        "brand": "Coinsource",
        "brand:wikidata": "Q109850339",
        "currency:XBT": "yes"
      }
    },
    {
      "displayName": "Cryptobase",
      "id": "cryptobase-93d3a2",
      "locationSet": {"include": ["us"]},
      "tags": {
        "amenity": "atm",
        "brand": "Cryptobase",
        "brand:wikidata": "Q122453754",
        "currency:XBT": "yes"
      }
    },
    {
      "displayName": "Deutsche Post",
      "id": "deutschepost-fb8bf5",
      "locationSet": {"include": ["de"]},
      "matchNames": ["deutsche post ag"],
      "tags": {
        "amenity": "atm",
        "brand": "Deutsche Post",
        "brand:wikidata": "Q157645"
      }
    },
    {
      "displayName": "Euronet",
      "id": "euronet-d5d850",
      "locationSet": {
        "include": ["001"],
        "exclude": ["cn"]
      },
      "matchNames": ["euronet 360 finance"],
      "tags": {
        "amenity": "atm",
        "brand": "Euronet",
        "brand:wikidata": "Q5412010",
        "operator": "Euronet",
        "operator:wikidata": "Q5412010"
      }
    },
    {
      "displayName": "Geldmaat",
      "id": "geldmaat-5333ab",
      "locationSet": {"include": ["nl"]},
      "tags": {
        "amenity": "atm",
        "brand": "Geldmaat",
        "brand:wikidata": "Q74051230",
        "operator": "Geldmaat",
        "operator:wikidata": "Q74051230"
      }
    },
    {
      "displayName": "Hitachi Money Spot ATM",
      "id": "hitachi-ad0527",
      "locationSet": {"include": ["in"]},
      "tags": {
        "amenity": "atm",
        "brand": "Hitachi",
        "brand:wikidata": "Q53238"
      }
    },
    {
      "displayName": "LibertyX",
      "id": "libertyx-93d3a2",
      "locationSet": {"include": ["us"]},
      "matchNames": ["libertyx bitcoin atm"],
      "matchTags": ["amenity/finance"],
      "tags": {
        "amenity": "atm",
        "brand": "LibertyX",
        "brand:wikidata": "Q109287417",
        "currency:XBT": "yes"
      }
    },
    {
      "displayName": "MEPS",
      "id": "meps-bc168a",
      "locationSet": {"include": ["my"]},
      "tags": {
        "amenity": "atm",
        "brand": "MEPS",
        "brand:wikidata": "Q6741957",
        "operator": "MEPS",
        "operator:wikidata": "Q6741957"
      }
    },
    {
      "displayName": "MoneyGet",
      "id": "moneyget-7535fc",
      "locationSet": {
        "include": ["al", "hr", "me", "rs"]
      },
      "tags": {
        "amenity": "atm",
        "brand": "MoneyGet",
        "brand:wikidata": "Q125808866",
        "operator": "Payten",
        "operator:wikidata": "Q125808773"
      }
    },
    {
      "displayName": "MoneyPass",
      "id": "moneypass-93d3a2",
      "locationSet": {"include": ["us"]},
      "tags": {
        "amenity": "atm",
        "brand": "MoneyPass",
        "brand:wikidata": "Q28447513"
      }
    },
    {
      "displayName": "NoteMachine",
      "id": "notemachine-396707",
      "locationSet": {"include": ["gb"]},
      "matchNames": ["notemachine ltd"],
      "tags": {
        "amenity": "atm",
        "brand": "NoteMachine",
        "brand:wikidata": "Q104368525",
        "operator": "NoteMachine",
        "operator:short": "NMATM",
        "operator:wikidata": "Q104368525"
      }
    },
    {
      "displayName": "Old Mutual",
      "id": "oldmutual-ff45b4",
      "locationSet": {
        "include": [
          "bw",
          "cn",
          "gh",
          "ke",
          "mw",
          "na",
          "ng",
          "rw",
          "ss",
          "sz",
          "tz",
          "ug",
          "za",
          "zw"
        ]
      },
      "tags": {
        "amenity": "atm",
        "brand": "Old Mutual",
        "brand:wikidata": "Q289704"
      }
    },
    {
      "displayName": "Pathward (MetaBank)",
      "id": "pathward-93d3a2",
      "locationSet": {"include": ["us"]},
      "matchNames": ["metabank"],
      "tags": {
        "amenity": "atm",
        "brand": "Pathward",
        "brand:wikidata": "Q6822267"
      }
    },
    {
      "displayName": "Planet Cash",
      "id": "planetcash-53bcca",
      "locationSet": {"include": ["pl"]},
      "tags": {
        "amenity": "atm",
        "brand": "Planet Cash",
        "brand:wikidata": "Q117744569",
        "operator": "ITCARD S.A.",
        "operator:wikidata": "Q117744575"
      }
    },
    {
      "displayName": "Post Office",
      "id": "postoffice-396707",
      "locationSet": {"include": ["gb"]},
      "matchNames": [
        "post office ltd",
        "post office money"
      ],
      "tags": {
        "amenity": "atm",
        "brand": "Post Office",
        "brand:wikidata": "Q1783168"
      }
    },
    {
      "displayName": "Postamat",
      "id": "postamat-64483a",
      "locationSet": {"include": ["it"]},
      "tags": {
        "amenity": "atm",
        "brand": "Postamat",
        "brand:wikidata": "Q3909447",
        "operator": "Poste Italiane",
        "operator:wikidata": "Q495026"
      }
    },
    {
      "displayName": "Postomat",
      "id": "postomat-ba97f3",
      "locationSet": {"include": ["ch"]},
      "tags": {
        "amenity": "atm",
        "brand": "Postomat",
        "brand:wikidata": "Q449233",
        "operator": "PostFinance"
      }
    },
    {
      "displayName": "RockItCoin",
      "id": "rockitcoin-93d3a2",
      "locationSet": {"include": ["us"]},
      "tags": {
        "amenity": "atm",
        "brand": "RockItCoin",
        "brand:wikidata": "Q125924689",
        "currency:XBT": "yes"
      }
    },
    {
      "displayName": "Sainsbury's Bank",
      "id": "sainsburysbank-396707",
      "locationSet": {"include": ["gb"]},
      "matchNames": ["sainsbury", "sainsbury's"],
      "tags": {
        "amenity": "atm",
        "brand": "Sainsbury's Bank",
        "brand:wikidata": "Q7400525",
        "operator": "Sainsbury's Bank",
        "operator:wikidata": "Q7400525"
      }
    },
    {
      "displayName": "Tesco Bank",
      "id": "tescobank-396707",
      "locationSet": {"include": ["gb"]},
      "matchNames": ["tesco"],
      "tags": {
        "amenity": "atm",
        "brand": "Tesco Bank",
        "brand:wikidata": "Q487494"
      }
    },
    {
      "displayName": "Тинькофф Банк",
      "id": "tinkoffbank-da35c8",
      "locationSet": {"include": ["ru"]},
      "matchNames": ["tinkoff", "тинькофф"],
      "tags": {
        "amenity": "atm",
        "brand": "Тинькофф Банк",
        "brand:en": "Tinkoff Bank",
        "brand:fa": "بانک تینکوف",
        "brand:he": "בנק טינקוף",
        "brand:ru": "Тинькофф Банк",
        "brand:wikidata": "Q4457878"
      }
    },
    {
      "displayName": "中華郵政",
      "id": "chunghwapost-9a6797",
      "locationSet": {"include": ["tw"]},
      "matchNames": ["中華郵政公司", "中華郵政股份有限公司"],
      "tags": {
        "alt_name": "中華郵政;郵局",
        "amenity": "atm",
        "brand": "中華郵政",
        "brand:en": "Chunghwa Post",
        "brand:nan": "Tiong-hôa Iû-chèng",
        "brand:nan-HJ": "中華郵政",
        "brand:nan-POJ": "Tiong-hôa Iû-chèng",
        "brand:nan-TL": "Tiong-huâ Iû-tsìng",
        "brand:wikidata": "Q709259",
        "brand:zh": "中華郵政"
      }
    }
  ]
}
