{
  "_meta": {
    "version": "6.0.20211103",
    "generated": "2021-11-03T04:58:50.376Z",
    "url": "https://raw.githubusercontent.com/osmlab/name-suggestion-index/main/dist/genericWords.json",
    "hash": "955d63d2a4b43ed2536f317f6dcfadea"
  },
  "genericWords": [
    "^(barn|bazaa?r|bench|bou?tique|building|casa|church)$",
    "^(baseball|basketball|football|soccer|softball|tennis(halle)?)\\s?(field|court)?$",
    "^(club|green|out|ware)\\s?house$",
    "^(driveway|el árbol|fountain|golf|government|graveyard)$",
    "^(fixme|n\\s?\\/?\\s?a|name|no\\s?name|none|null|temporary|test|unknown)$",
    "^(hofladen|librairie|magazine?|maison)$",
    "^(mobile home|skate)?\\s?park$",
    "^(obuwie|pond|pool|sale|shops?|sklep|stores?)$",
    "^\\?+$",
    "^private$",
    "^tattoo( studio)?$",
    "^windmill$",
    "^церковная( лавка)?$"
  ]
}
