{
  "properties": {
    "path": "operators/amenity/community_centre",
    "exclude": {"generic": ["^(community centre|government)$"]}
  },
  "items": [
    {
      "displayName": "Auckland Council",
      "id": "aucklandcouncil-8f36f1",
      "locationSet": {
        "include": ["nz-auk.geojson"]
      },
      "tags": {
        "amenity": "community_centre",
        "operator": "Auckland Council",
        "operator:type": "government",
        "operator:wikidata": "Q758635"
      }
    }
  ]
}
