{
  "amenity/fuel|1-2-3": {
    "count": 62,
    "tags": {
      "amenity": "fuel",
      "brand": "1-2-3",
      "brand:wikidata": "Q4545742",
      "brand:wikipedia": "en:1-2-3 (fuel station)",
      "name": "1-2-3"
    }
  },
  "amenity/fuel|7-Eleven": {
    "count": 1062,
    "match": [
      "amenity/fuel|7 Eleven",
      "amenity/fuel|7-11"
    ],
    "nomatch": ["shop/convenience|7-Eleven"],
    "tags": {
      "amenity": "fuel",
      "brand": "7-Eleven",
      "brand:wikidata": "Q259340",
      "brand:wikipedia": "en:7-Eleven",
      "name": "7-Eleven"
    }
  },
  "amenity/fuel|ABC": {
    "count": 85,
    "countryCodes": ["fi"],
    "nomatch": ["shop/convenience|ABC"],
    "tags": {
      "amenity": "fuel",
      "brand": "ABC",
      "brand:wikidata": "Q10397504",
      "brand:wikipedia": "fi:ABC-ketju",
      "name": "ABC"
    }
  },
  "amenity/fuel|ADNOC": {
    "nocount": true,
    "tags": {
      "amenity": "fuel",
      "brand": "ADNOC",
      "brand:wikidata": "Q166729",
      "brand:wikipedia": "en:Abu Dhabi National Oil Company",
      "name": "ADNOC"
    }
  },
  "amenity/fuel|ANP": {
    "count": 233,
    "tags": {
      "amenity": "fuel",
      "brand": "ANP",
      "name": "ANP"
    }
  },
  "amenity/fuel|Aegean": {
    "count": 100,
    "countryCodes": ["gr"],
    "tags": {
      "amenity": "fuel",
      "brand": "Aegean",
      "brand:wikidata": "Q28146598",
      "brand:wikipedia": "el:Aegean Oil",
      "name": "Aegean"
    }
  },
  "amenity/fuel|Afriquia": {
    "count": 189,
    "tags": {
      "amenity": "fuel",
      "brand": "Afriquia",
      "brand:wikidata": "Q2829178",
      "brand:wikipedia": "en:Akwa Group",
      "name": "Afriquia"
    }
  },
  "amenity/fuel|Agip": {
    "count": 1979,
    "match": ["amenity/fuel|AGIP"],
    "tags": {
      "amenity": "fuel",
      "brand": "Agip",
      "brand:wikidata": "Q377915",
      "brand:wikipedia": "en:Agip",
      "name": "Agip"
    }
  },
  "amenity/fuel|Agrola": {
    "count": 111,
    "tags": {
      "amenity": "fuel",
      "brand": "Agrola",
      "brand:wikidata": "Q397351",
      "brand:wikipedia": "de:Agrola",
      "name": "Agrola"
    }
  },
  "amenity/fuel|Alon": {
    "count": 74,
    "countryCodes": ["us"],
    "tags": {
      "amenity": "fuel",
      "brand": "Alon",
      "brand:wikidata": "Q62274304",
      "name": "Alon"
    }
  },
  "amenity/fuel|Alpet": {
    "count": 78,
    "countryCodes": ["al", "tr"],
    "tags": {
      "amenity": "fuel",
      "brand": "Alpet",
      "brand:wikidata": "Q62131561",
      "name": "Alpet"
    }
  },
  "amenity/fuel|Api": {
    "count": 213,
    "tags": {
      "amenity": "fuel",
      "brand": "Api",
      "brand:wikidata": "Q466043",
      "brand:wikipedia": "en:American Petroleum Institute",
      "name": "Api"
    }
  },
  "amenity/fuel|Aral": {
    "count": 1437,
    "countryCodes": ["de"],
    "match": [
      "amenity/fuel|ARAL",
      "amenity/fuel|Aral Tankstelle",
      "shop/convenience|Aral",
      "shop/kiosk|Aral"
    ],
    "tags": {
      "amenity": "fuel",
      "brand": "Aral",
      "brand:wikidata": "Q565734",
      "brand:wikipedia": "en:Aral AG",
      "name": "Aral"
    }
  },
  "amenity/fuel|Arco": {
    "count": 505,
    "match": ["amenity/fuel|ARCO"],
    "tags": {
      "amenity": "fuel",
      "brand": "Arco",
      "brand:wikidata": "Q304769",
      "brand:wikipedia": "en:ARCO",
      "name": "Arco"
    }
  },
  "amenity/fuel|Asda": {
    "count": 66,
    "countryCodes": ["gb"],
    "nomatch": [
      "shop/fuel|Asda",
      "shop/supermarket|ASDA"
    ],
    "tags": {
      "amenity": "fuel",
      "brand": "Asda",
      "brand:wikidata": "Q297410",
      "brand:wikipedia": "en:Asda",
      "name": "Asda"
    }
  },
  "amenity/fuel|Atem": {
    "countryCodes": ["br"],
    "match": ["amenity/fuel|Posto Atem"],
    "nocount": true,
    "tags": {
      "amenity": "fuel",
      "brand": "Atem",
      "brand:wikidata": "Q62332255",
      "name": "Atem"
    }
  },
  "amenity/fuel|Auchan": {
    "count": 101,
    "nomatch": ["shop/supermarket|Auchan"],
    "tags": {
      "amenity": "fuel",
      "brand": "Auchan",
      "brand:wikidata": "Q758603",
      "brand:wikipedia": "en:Auchan",
      "name": "Auchan"
    }
  },
  "amenity/fuel|Avanti": {
    "count": 105,
    "countryCodes": ["at"],
    "tags": {
      "amenity": "fuel",
      "brand": "Avanti",
      "brand:wikidata": "Q168238",
      "brand:wikipedia": "en:OMV",
      "name": "Avanti"
    }
  },
  "amenity/fuel|Avia": {
    "count": 808,
    "match": [
      "amenity/fuel|AVIA",
      "amenity/fuel|Station Avia"
    ],
    "tags": {
      "amenity": "fuel",
      "brand": "Avia",
      "brand:wikidata": "Q300147",
      "brand:wikipedia": "de:Avia International",
      "name": "Avia"
    }
  },
  "amenity/fuel|Avin": {
    "count": 75,
    "countryCodes": ["gr"],
    "tags": {
      "amenity": "fuel",
      "brand": "Avin",
      "brand:wikidata": "Q19903165",
      "brand:wikipedia": "en:Avin International",
      "name": "Avin"
    }
  },
  "amenity/fuel|Axion": {
    "count": 117,
    "countryCodes": ["ar", "py", "uy"],
    "tags": {
      "amenity": "fuel",
      "brand": "Axion",
      "brand:wikidata": "Q62131749",
      "name": "Axion"
    }
  },
  "amenity/fuel|Aytemiz": {
    "count": 74,
    "countryCodes": ["tr"],
    "tags": {
      "amenity": "fuel",
      "brand": "Aytemiz",
      "brand:wikidata": "Q62274352",
      "name": "Aytemiz"
    }
  },
  "amenity/fuel|BEBECO": {
    "count": 67,
    "countryCodes": ["ch"],
    "tags": {
      "amenity": "fuel",
      "brand": "BEBECO",
      "brand:wikidata": "Q62274373",
      "name": "BEBECO"
    }
  },
  "amenity/fuel|BHPetrol": {
    "count": 96,
    "countryCodes": ["my"],
    "tags": {
      "amenity": "fuel",
      "brand": "BHPetrol",
      "brand:wikidata": "Q62274381",
      "name": "BHPetrol"
    }
  },
  "amenity/fuel|BP": {
    "count": 4865,
    "match": [
      "amenity/fuel|Bp",
      "amenity/fuel|bp"
    ],
    "nomatch": ["shop/convenience|BP Shop"],
    "tags": {
      "amenity": "fuel",
      "brand": "BP",
      "brand:wikidata": "Q152057",
      "brand:wikipedia": "en:BP",
      "name": "BP"
    }
  },
  "amenity/fuel|BR": {
    "count": 193,
    "countryCodes": ["br"],
    "match": [
      "amenity/fuel|BR Petrobras",
      "amenity/fuel|Petrobras",
      "amenity/fuel|Posto BR"
    ],
    "tags": {
      "amenity": "fuel",
      "brand": "BR",
      "brand:wikidata": "Q4836468",
      "brand:wikipedia": "pt:Petrobras Distribuidora",
      "name": "BR"
    }
  },
  "amenity/fuel|Bangchak": {
    "count": 144,
    "tags": {
      "amenity": "fuel",
      "brand": "Bangchak",
      "brand:wikidata": "Q6579719",
      "brand:wikipedia": "zh:曼差石油股份",
      "name": "Bangchak"
    }
  },
  "amenity/fuel|Bharat Petroleum": {
    "count": 354,
    "countryCodes": ["in"],
    "tags": {
      "amenity": "fuel",
      "brand": "Bharat Petroleum",
      "brand:wikidata": "Q854826",
      "brand:wikipedia": "en:Bharat Petroleum",
      "name": "Bharat Petroleum"
    }
  },
  "amenity/fuel|Biomax": {
    "count": 73,
    "countryCodes": ["co"],
    "tags": {
      "amenity": "fuel",
      "brand": "Biomax",
      "brand:wikidata": "Q62274413",
      "name": "Biomax"
    }
  },
  "amenity/fuel|Bliska": {
    "count": 108,
    "countryCodes": ["pl"],
    "tags": {
      "amenity": "fuel",
      "brand": "Bliska",
      "brand:wikidata": "Q4016378",
      "brand:wikipedia": "pl:Bliska",
      "name": "Bliska"
    }
  },
  "amenity/fuel|CAMPSA": {
    "count": 284,
    "countryCodes": ["es"],
    "match": ["amenity/fuel|Campsa"],
    "tags": {
      "amenity": "fuel",
      "brand": "CAMPSA",
      "brand:wikidata": "Q1031623",
      "brand:wikipedia": "en:Campsa",
      "name": "CAMPSA"
    }
  },
  "amenity/fuel|CEPSA": {
    "count": 760,
    "match": ["amenity/fuel|Cepsa"],
    "tags": {
      "amenity": "fuel",
      "brand": "CEPSA",
      "brand:wikidata": "Q608819",
      "brand:wikipedia": "en:Compañía Española de Petróleos",
      "name": "CEPSA"
    }
  },
  "amenity/fuel|Caltex": {
    "count": 1786,
    "tags": {
      "amenity": "fuel",
      "brand": "Caltex",
      "brand:wikidata": "Q277470",
      "brand:wikipedia": "en:Caltex",
      "name": "Caltex"
    }
  },
  "amenity/fuel|Canadian Tire Gas+": {
    "match": [
      "amenity/fuel|Canadian Tire",
      "amenity/fuel|Canadian Tire Gas Bar"
    ],
    "nocount": true,
    "nomatch": [
      "shop/department_store|Canadian Tire"
    ],
    "tags": {
      "amenity": "fuel",
      "brand": "Canadian Tire",
      "brand:wikidata": "Q1032400",
      "brand:wikipedia": "en:Canadian Tire",
      "name": "Canadian Tire"
    }
  },
  "amenity/fuel|Carrefour": {
    "count": 323,
    "tags": {
      "amenity": "fuel",
      "brand": "Carrefour",
      "name": "Carrefour"
    }
  },
  "amenity/fuel|Carrefour Market": {
    "count": 133,
    "nomatch": [
      "shop/supermarket|Carrefour Market"
    ],
    "tags": {
      "amenity": "fuel",
      "brand": "Carrefour Market",
      "brand:wikidata": "Q217599",
      "brand:wikipedia": "en:Carrefour",
      "name": "Carrefour Market"
    }
  },
  "amenity/fuel|Casey's General Store": {
    "count": 439,
    "match": ["amenity/fuel|Casey's"],
    "nomatch": [
      "shop/convenience|Casey's General Store"
    ],
    "tags": {
      "amenity": "fuel",
      "brand": "Casey's General Store",
      "brand:wikidata": "Q2940968",
      "brand:wikipedia": "en:Casey's General Stores",
      "name": "Casey's General Store"
    }
  },
  "amenity/fuel|Casino": {
    "count": 51,
    "tags": {
      "amenity": "fuel",
      "brand": "Casino",
      "name": "Casino"
    }
  },
  "amenity/fuel|Cenex": {
    "count": 273,
    "tags": {
      "amenity": "fuel",
      "brand": "Cenex",
      "brand:wikidata": "Q5011381",
      "brand:wikipedia": "en:CHS Inc.",
      "name": "Cenex"
    }
  },
  "amenity/fuel|Ceypetco": {
    "count": 76,
    "countryCodes": ["lk"],
    "match": [
      "amenity/fuel|Lanka Filling Station"
    ],
    "tags": {
      "amenity": "fuel",
      "brand": "Ceypetco",
      "brand:wikidata": "Q5065795",
      "brand:wikipedia": "en:Ceylon Petroleum Corporation",
      "name": "Ceypetco"
    }
  },
  "amenity/fuel|Chevron": {
    "count": 2153,
    "nomatch": ["shop/convenience|Chevron"],
    "tags": {
      "amenity": "fuel",
      "brand": "Chevron",
      "brand:wikidata": "Q319642",
      "brand:wikipedia": "en:Chevron Corporation",
      "name": "Chevron"
    }
  },
  "amenity/fuel|Circle K": {
    "count": 1188,
    "nomatch": ["shop/convenience|Circle K"],
    "tags": {
      "amenity": "fuel",
      "brand": "Circle K",
      "brand:wikidata": "Q3268010",
      "brand:wikipedia": "en:Circle K",
      "name": "Circle K"
    }
  },
  "amenity/fuel|Citgo": {
    "count": 950,
    "nomatch": ["shop/convenience|Citgo"],
    "tags": {
      "amenity": "fuel",
      "brand": "Citgo",
      "brand:wikidata": "Q2974437",
      "brand:wikipedia": "en:Citgo",
      "name": "Citgo"
    }
  },
  "amenity/fuel|Clark": {
    "count": 65,
    "tags": {
      "amenity": "fuel",
      "brand": "Clark",
      "brand:wikidata": "Q5127157",
      "brand:wikipedia": "en:Clark Brands",
      "name": "Clark"
    }
  },
  "amenity/fuel|Classic": {
    "count": 52,
    "tags": {
      "amenity": "fuel",
      "brand": "Classic",
      "name": "Classic"
    }
  },
  "amenity/fuel|Co-op": {
    "count": 293,
    "match": [
      "amenity/fuel|Co-Op",
      "amenity/fuel|Coop"
    ],
    "nomatch": [
      "shop/convenience|Co-op",
      "shop/supermarket|Co-op"
    ],
    "tags": {
      "amenity": "fuel",
      "brand": "Federated Co-operatives",
      "brand:wikidata": "Q5440676",
      "brand:wikipedia": "en:Federated Co-operatives",
      "name": "Co-op"
    }
  },
  "amenity/fuel|Coles Express": {
    "count": 342,
    "countryCodes": ["au"],
    "nomatch": ["shop/convenience|Coles Express"],
    "tags": {
      "amenity": "fuel",
      "brand": "Coles Express",
      "brand:wikidata": "Q5144653",
      "brand:wikipedia": "en:Coles Express",
      "name": "Coles Express"
    }
  },
  "amenity/fuel|Conoco": {
    "count": 523,
    "tags": {
      "amenity": "fuel",
      "brand": "Conoco",
      "brand:wikidata": "Q1126518",
      "brand:wikipedia": "en:Conoco",
      "name": "Conoco"
    }
  },
  "amenity/fuel|Copec": {
    "count": 627,
    "countryCodes": ["cl"],
    "tags": {
      "amenity": "fuel",
      "brand": "Copec",
      "brand:wikidata": "Q11681461",
      "brand:wikipedia": "en:Empresas Copec",
      "name": "Copec"
    }
  },
  "amenity/fuel|Copetrol": {
    "count": 151,
    "countryCodes": ["py"],
    "tags": {
      "amenity": "fuel",
      "brand": "Copetrol",
      "brand:wikidata": "Q62274431",
      "name": "Copetrol"
    }
  },
  "amenity/fuel|Cosmo": {
    "count": 84,
    "countryCodes": ["jp"],
    "tags": {
      "amenity": "fuel",
      "brand": "Cosmo",
      "brand:wikidata": "Q2498318",
      "brand:wikipedia": "en:Cosmo Oil Company",
      "name": "Cosmo"
    }
  },
  "amenity/fuel|Costco Gasoline": {
    "count": 241,
    "match": [
      "amenity/fuel|Costco",
      "amenity/fuel|Costco Gas",
      "amenity/fuel|Costco Wholesale"
    ],
    "nomatch": [
      "amenity/pharmacy|Costco Pharmacy",
      "shop/wholesale|Costco"
    ],
    "tags": {
      "amenity": "fuel",
      "brand": "Costco Gasoline",
      "brand:wikidata": "Q715583",
      "brand:wikipedia": "en:Costco",
      "name": "Costco Gasoline"
    }
  },
  "amenity/fuel|Couche-Tard": {
    "count": 71,
    "countryCodes": ["ca"],
    "nomatch": ["shop/convenience|Couche-Tard"],
    "tags": {
      "amenity": "fuel",
      "brand": "Couche-Tard",
      "brand:wikidata": "Q2836957",
      "brand:wikipedia": "en:Alimentation Couche-Tard",
      "name": "Couche-Tard"
    }
  },
  "amenity/fuel|Crevier": {
    "count": 118,
    "countryCodes": ["ca"],
    "tags": {
      "amenity": "fuel",
      "brand": "Crevier",
      "brand:wikidata": "Q61743451",
      "name": "Crevier"
    }
  },
  "amenity/fuel|Crodux": {
    "count": 56,
    "countryCodes": ["hr"],
    "tags": {
      "amenity": "fuel",
      "brand": "Crodux",
      "brand:wikidata": "Q62274622",
      "name": "Crodux"
    }
  },
  "amenity/fuel|Cumberland Farms": {
    "count": 131,
    "countryCodes": ["us"],
    "nomatch": [
      "shop/convenience|Cumberland Farms"
    ],
    "tags": {
      "amenity": "fuel",
      "brand": "Cumberland Farms",
      "brand:wikidata": "Q1143685",
      "brand:wikipedia": "en:Cumberland Farms",
      "name": "Cumberland Farms"
    }
  },
  "amenity/fuel|Delta~(Panama & Costa Rica)": {
    "countryCodes": ["cr", "pr"],
    "nocount": true,
    "tags": {
      "amenity": "fuel",
      "brand": "Delta",
      "brand:wikidata": "Q62274638",
      "name": "Delta"
    }
  },
  "amenity/fuel|Delta~(USA)": {
    "countryCodes": ["us"],
    "nocount": true,
    "tags": {
      "amenity": "fuel",
      "brand": "Delta",
      "brand:wikidata": "Q62274661",
      "name": "Delta"
    }
  },
  "amenity/fuel|Depot Tela": {
    "count": 59,
    "tags": {
      "amenity": "fuel",
      "brand": "Depot Tela",
      "name": "Depot Tela"
    }
  },
  "amenity/fuel|Diamond Shamrock": {
    "count": 57,
    "countryCodes": ["us"],
    "tags": {
      "amenity": "fuel",
      "brand": "Diamond Shamrock",
      "brand:wikidata": "Q16973722",
      "brand:wikipedia": "en:Diamond Shamrock",
      "name": "Diamond Shamrock"
    }
  },
  "amenity/fuel|Domo": {
    "count": 59,
    "countryCodes": ["ca"],
    "tags": {
      "amenity": "fuel",
      "brand": "Domo",
      "brand:wikidata": "Q5291326",
      "brand:wikipedia": "en:Domo Gasoline",
      "name": "Domo"
    }
  },
  "amenity/fuel|EKO~(Canada)": {
    "countryCodes": ["ca"],
    "match": ["amenity/fuel|Eko~(Canada)"],
    "nocount": true,
    "nomatch": [
      "amenity/fuel|EKO~(Greece)",
      "shop/supermarket|Eko"
    ],
    "tags": {
      "amenity": "fuel",
      "brand": "EKO",
      "brand:wikidata": "Q3045934",
      "brand:wikipedia": "fr:EKO",
      "name": "EKO"
    }
  },
  "amenity/fuel|EKO~(Greece)": {
    "countryCodes": [
      "bg",
      "cy",
      "gr",
      "me",
      "mk",
      "rs"
    ],
    "match": [
      "amenity/fuel|Eko~(Greece)",
      "amenity/fuel|ΕΚΟ"
    ],
    "nocount": true,
    "nomatch": [
      "amenity/fuel|EKO~(Canada)",
      "shop/supermarket|Eko"
    ],
    "tags": {
      "amenity": "fuel",
      "brand": "EKO",
      "brand:wikidata": "Q903198",
      "brand:wikipedia": "el:Ελληνικά Πετρέλαια",
      "name": "EKO"
    }
  },
  "amenity/fuel|ENEOS": {
    "count": 2081,
    "countryCodes": ["jp"],
    "match": ["amenity/fuel|Eneos"],
    "tags": {
      "amenity": "fuel",
      "brand": "ENEOS",
      "brand:wikidata": "Q1640290",
      "brand:wikipedia": "en:JXTG Nippon Oil & Energy",
      "name": "ENEOS"
    }
  },
  "amenity/fuel|Elan": {
    "count": 219,
    "countryCodes": ["de", "fr", "nl"],
    "tags": {
      "amenity": "fuel",
      "brand": "Elan",
      "brand:wikidata": "Q57980752",
      "name": "Elan"
    }
  },
  "amenity/fuel|Engen": {
    "count": 546,
    "tags": {
      "amenity": "fuel",
      "brand": "Engen",
      "brand:wikidata": "Q3054251",
      "brand:wikipedia": "en:Engen Petroleum",
      "name": "Engen"
    }
  },
  "amenity/fuel|Eni": {
    "count": 887,
    "match": [
      "amenity/fuel|ENI",
      "amenity/fuel|eni"
    ],
    "tags": {
      "amenity": "fuel",
      "brand": "Eni",
      "brand:wikidata": "Q565594",
      "brand:wikipedia": "en:Eni",
      "name": "Eni"
    }
  },
  "amenity/fuel|Erg": {
    "count": 420,
    "match": ["amenity/fuel|ERG"],
    "tags": {
      "amenity": "fuel",
      "brand": "Erg",
      "brand:wikidata": "Q739503",
      "brand:wikipedia": "it:ERG (azienda)",
      "name": "Erg"
    }
  },
  "amenity/fuel|Esso": {
    "count": 5178,
    "match": [
      "amenity/fuel|ESSO",
      "amenity/fuel|Station Esso"
    ],
    "nomatch": [
      "amenity/fuel|Esso Express",
      "shop/convenience|Esso"
    ],
    "tags": {
      "amenity": "fuel",
      "brand": "Esso",
      "brand:wikidata": "Q867662",
      "brand:wikipedia": "en:Esso",
      "name": "Esso"
    }
  },
  "amenity/fuel|Esso Express": {
    "count": 202,
    "nomatch": ["amenity/fuel|Esso"],
    "tags": {
      "amenity": "fuel",
      "brand": "Esso Express",
      "brand:wikidata": "Q2350336",
      "brand:wikipedia": "nl:Esso Express",
      "name": "Esso Express"
    }
  },
  "amenity/fuel|Exxon": {
    "count": 1512,
    "tags": {
      "amenity": "fuel",
      "brand": "Exxon",
      "brand:wikidata": "Q4781944",
      "brand:wikipedia": "en:Exxon",
      "name": "Exxon"
    }
  },
  "amenity/fuel|F24": {
    "count": 96,
    "countryCodes": ["dk"],
    "tags": {
      "amenity": "fuel",
      "brand": "F24",
      "brand:wikidata": "Q12310853",
      "brand:wikipedia": "da:F24",
      "name": "F24"
    }
  },
  "amenity/fuel|Fas Gas": {
    "count": 157,
    "match": ["amenity/fuel|Fas Gas Plus"],
    "tags": {
      "amenity": "fuel",
      "brand": "Fas Gas",
      "brand:wikidata": "Q61743505",
      "brand:wikipedia": "en:Parkland Fuel",
      "name": "Fas Gas"
    }
  },
  "amenity/fuel|Firezone": {
    "count": 74,
    "countryCodes": ["nl"],
    "tags": {
      "amenity": "fuel",
      "brand": "Firezone",
      "brand:wikidata": "Q14628080",
      "brand:wikipedia": "nl:Firezone",
      "name": "Firezone"
    }
  },
  "amenity/fuel|Flying V": {
    "count": 190,
    "countryCodes": ["ph"],
    "tags": {
      "amenity": "fuel",
      "brand": "Flying V",
      "brand:wikidata": "Q62275048",
      "name": "Flying V"
    }
  },
  "amenity/fuel|Freie Tankstelle": {
    "count": 199,
    "countryCodes": ["de"],
    "tags": {
      "amenity": "fuel",
      "brand": "Freie Tankstelle",
      "brand:wikidata": "Q1009104",
      "brand:wikipedia": "de:Bundesverband freier Tankstellen",
      "name": "Freie Tankstelle"
    }
  },
  "amenity/fuel|GALP": {
    "count": 487,
    "match": ["amenity/fuel|Galp"],
    "tags": {
      "amenity": "fuel",
      "brand": "GALP",
      "brand:wikidata": "Q1492739",
      "brand:wikipedia": "en:Galp Energia",
      "name": "GALP"
    }
  },
  "amenity/fuel|Gazel": {
    "count": 64,
    "countryCodes": ["co", "mx", "pe"],
    "tags": {
      "amenity": "fuel",
      "brand": "Gazel",
      "brand:wikidata": "Q62529885",
      "name": "Gazel"
    }
  },
  "amenity/fuel|Gazprom": {
    "count": 67,
    "tags": {
      "amenity": "fuel",
      "brand": "Gazprom",
      "brand:wikidata": "Q102673",
      "brand:wikipedia": "en:Gazprom",
      "name": "Gazprom"
    }
  },
  "amenity/fuel|GetGo": {
    "count": 77,
    "countryCodes": ["us"],
    "tags": {
      "amenity": "fuel",
      "brand": "GetGo",
      "brand:wikidata": "Q5553766",
      "brand:wikipedia": "en:GetGo",
      "name": "GetGo"
    }
  },
  "amenity/fuel|Glusco": {
    "count": 122,
    "countryCodes": ["ua"],
    "tags": {
      "amenity": "fuel",
      "brand": "Glusco",
      "brand:wikidata": "Q62284719",
      "name": "Glusco"
    }
  },
  "amenity/fuel|Goil": {
    "count": 156,
    "tags": {
      "amenity": "fuel",
      "brand": "Goil",
      "brand:wikidata": "Q5555383",
      "brand:wikipedia": "en:Ghana Oil Company",
      "name": "Goil"
    }
  },
  "amenity/fuel|Gulf": {
    "count": 561,
    "tags": {
      "amenity": "fuel",
      "brand": "Gulf",
      "brand:wikidata": "Q1296860",
      "brand:wikipedia": "en:Gulf Oil",
      "name": "Gulf"
    }
  },
  "amenity/fuel|Gull": {
    "count": 57,
    "tags": {
      "amenity": "fuel",
      "brand": "Gull",
      "brand:wikidata": "Q5617739",
      "brand:wikipedia": "en:Gull Petroleum",
      "name": "Gull"
    }
  },
  "amenity/fuel|H-E-B Fuel": {
    "count": 232,
    "match": ["amenity/fuel|H-E-B Gas"],
    "nomatch": ["shop/supermarket|H-E-B"],
    "tags": {
      "amenity": "fuel",
      "brand": "H-E-B Fuel",
      "brand:wikidata": "Q830621",
      "brand:wikipedia": "en:H-E-B",
      "name": "H-E-B Fuel"
    }
  },
  "amenity/fuel|HEM": {
    "count": 286,
    "countryCodes": ["de"],
    "match": ["amenity/fuel|Hem"],
    "tags": {
      "amenity": "fuel",
      "brand": "HEM",
      "brand:wikidata": "Q1563517",
      "brand:wikipedia": "de:Deutsche Tamoil",
      "name": "HEM"
    }
  },
  "amenity/fuel|HP": {
    "count": 180,
    "match": [
      "amenity/fuel|H P",
      "amenity/fuel|HP Petrol Pump",
      "amenity/fuel|Hindustan Petroleum"
    ],
    "tags": {
      "amenity": "fuel",
      "brand": "Hindustan Petroleum",
      "brand:wikidata": "Q1619375",
      "brand:wikipedia": "en:Hindustan Petroleum",
      "name": "HP",
      "official_name": "Hindustan Petroleum"
    }
  },
  "amenity/fuel|Harnois": {
    "count": 53,
    "countryCodes": ["ca"],
    "tags": {
      "amenity": "fuel",
      "brand": "Harnois",
      "brand:wikidata": "Q61743558",
      "name": "Harnois"
    }
  },
  "amenity/fuel|Hess": {
    "count": 159,
    "tags": {
      "amenity": "fuel",
      "brand": "Hess",
      "brand:wikidata": "Q1615684",
      "brand:wikipedia": "en:Hess Corporation",
      "name": "Hess"
    }
  },
  "amenity/fuel|Hofer": {
    "count": 72,
    "countryCodes": ["at", "si"],
    "nomatch": ["shop/supermarket|Hofer"],
    "tags": {
      "amenity": "fuel",
      "brand": "Hofer",
      "brand:wikidata": "Q15815751",
      "brand:wikipedia": "de:Hofer KG",
      "name": "Hofer"
    }
  },
  "amenity/fuel|Holiday": {
    "count": 204,
    "countryCodes": ["us"],
    "nomatch": ["shop/convenience|Holiday"],
    "tags": {
      "amenity": "fuel",
      "brand": "Holiday",
      "brand:wikidata": "Q5880490",
      "brand:wikipedia": "en:Holiday Stationstores",
      "name": "Holiday"
    }
  },
  "amenity/fuel|Husky": {
    "count": 381,
    "countryCodes": ["ca"],
    "nomatch": ["shop/convenience|Husky"],
    "tags": {
      "amenity": "fuel",
      "brand": "Husky",
      "name": "Husky"
    }
  },
  "amenity/fuel|IES": {
    "count": 51,
    "countryCodes": ["it"],
    "tags": {
      "amenity": "fuel",
      "brand": "IES",
      "brand:wikidata": "Q62287387",
      "name": "IES"
    }
  },
  "amenity/fuel|IP": {
    "count": 986,
    "tags": {
      "amenity": "fuel",
      "brand": "IP",
      "brand:wikidata": "Q646807",
      "brand:wikipedia": "en:Anonima Petroli Italiana",
      "name": "IP"
    }
  },
  "amenity/fuel|Indian Oil": {
    "count": 578,
    "tags": {
      "amenity": "fuel",
      "brand": "Indian Oil",
      "brand:wikidata": "Q1289348",
      "brand:wikipedia": "en:Indian Oil Corporation",
      "name": "Indian Oil"
    }
  },
  "amenity/fuel|Indian Oil Petrol Pump": {
    "count": 52,
    "tags": {
      "amenity": "fuel",
      "brand": "Indian Oil Petrol Pump",
      "name": "Indian Oil Petrol Pump"
    }
  },
  "amenity/fuel|Ingo": {
    "count": 196,
    "tags": {
      "amenity": "fuel",
      "brand": "Ingo",
      "brand:wikidata": "Q17048617",
      "brand:wikipedia": "en:Ingo (brand)",
      "name": "Ingo"
    }
  },
  "amenity/fuel|Intermarché": {
    "count": 623,
    "match": ["amenity/fuel|Intermarché Super"],
    "nomatch": ["shop/supermarket|Intermarché"],
    "tags": {
      "amenity": "fuel",
      "brand": "Intermarché",
      "brand:wikidata": "Q3153200",
      "brand:wikipedia": "fr:Intermarché",
      "name": "Intermarché"
    }
  },
  "amenity/fuel|Ipiranga": {
    "count": 208,
    "countryCodes": ["br"],
    "match": ["amenity/fuel|Posto Ipiranga"],
    "tags": {
      "amenity": "fuel",
      "brand": "Ipiranga",
      "brand:wikidata": "Q2081136",
      "brand:wikipedia": "pt:Ipiranga (empresa)",
      "name": "Ipiranga"
    }
  },
  "amenity/fuel|Irving": {
    "count": 439,
    "nomatch": ["shop/convenience|Irving"],
    "tags": {
      "amenity": "fuel",
      "brand": "Irving",
      "brand:wikidata": "Q1673286",
      "brand:wikipedia": "en:Irving Oil",
      "name": "Irving"
    }
  },
  "amenity/fuel|JA-SS": {
    "count": 159,
    "countryCodes": ["jp"],
    "match": ["amenity/fuel|JA"],
    "tags": {
      "amenity": "fuel",
      "brand": "JA-SS",
      "brand:wikidata": "Q11225213",
      "brand:wikipedia": "ja:JA-SS",
      "name": "JA-SS"
    }
  },
  "amenity/fuel|Jet": {
    "count": 522,
    "match": ["amenity/fuel|JET"],
    "nomatch": ["shop/clothes|Jet"],
    "tags": {
      "amenity": "fuel",
      "brand": "Jet",
      "brand:wikidata": "Q568940",
      "brand:wikipedia": "en:Jet (brand)",
      "name": "Jet"
    }
  },
  "amenity/fuel|Jetti": {
    "count": 70,
    "countryCodes": ["ph"],
    "tags": {
      "amenity": "fuel",
      "brand": "Jetti",
      "brand:wikidata": "Q62288720",
      "name": "Jetti"
    }
  },
  "amenity/fuel|Kangaroo": {
    "count": 106,
    "nomatch": ["shop/convenience|Kangaroo"],
    "tags": {
      "amenity": "fuel",
      "brand": "Kangaroo",
      "name": "Kangaroo"
    }
  },
  "amenity/fuel|Kobil": {
    "count": 110,
    "tags": {
      "amenity": "fuel",
      "brand": "Kobil",
      "brand:wikidata": "Q22906119",
      "brand:wikipedia": "en:KenolKobil",
      "name": "Kobil"
    }
  },
  "amenity/fuel|Kroger": {
    "count": 95,
    "match": ["amenity/fuel|Kroger Fuel"],
    "nomatch": ["shop/supermarket|Kroger"],
    "tags": {
      "amenity": "fuel",
      "brand": "Kroger",
      "brand:wikidata": "Q153417",
      "brand:wikipedia": "en:Kroger",
      "name": "Kroger"
    }
  },
  "amenity/fuel|Kum & Go": {
    "count": 179,
    "countryCodes": ["us"],
    "nomatch": ["shop/convenience|Kum & Go"],
    "tags": {
      "amenity": "fuel",
      "brand": "Kum & Go",
      "brand:wikidata": "Q6443340",
      "brand:wikipedia": "en:Kum & Go",
      "name": "Kum & Go"
    }
  },
  "amenity/fuel|Kwik Trip": {
    "count": 288,
    "nomatch": ["shop/convenience|Kwik Trip"],
    "tags": {
      "amenity": "fuel",
      "brand": "Kwik Trip",
      "brand:wikidata": "Q6450420",
      "brand:wikipedia": "en:Kwik Trip",
      "name": "Kwik Trip"
    }
  },
  "amenity/fuel|Liberty": {
    "count": 122,
    "nomatch": ["amenity/bank|Liberty Bank"],
    "tags": {
      "amenity": "fuel",
      "brand": "Liberty",
      "name": "Liberty"
    }
  },
  "amenity/fuel|Lotos": {
    "count": 299,
    "nomatch": ["amenity/fuel|Lotos Optima"],
    "tags": {
      "amenity": "fuel",
      "brand": "Lotos",
      "brand:wikidata": "Q1256909",
      "brand:wikipedia": "en:Grupa Lotos",
      "name": "Lotos"
    }
  },
  "amenity/fuel|Lotos Optima": {
    "count": 87,
    "nomatch": ["amenity/fuel|Lotos"],
    "tags": {
      "amenity": "fuel",
      "brand": "Lotos Optima",
      "brand:wikidata": "Q1256909",
      "brand:wikipedia": "en:Grupa Lotos",
      "name": "Lotos Optima"
    }
  },
  "amenity/fuel|Love's": {
    "count": 92,
    "countryCodes": ["us"],
    "tags": {
      "amenity": "fuel",
      "brand": "Love's",
      "brand:wikidata": "Q1872496",
      "brand:wikipedia": "en:Love's Travel Stops & Country Stores",
      "name": "Love's"
    }
  },
  "amenity/fuel|Lukoil": {
    "count": 917,
    "match": [
      "amenity/fuel|LUKOIL",
      "amenity/fuel|LukOil"
    ],
    "tags": {
      "amenity": "fuel",
      "brand": "Lukoil",
      "brand:wikidata": "Q329347",
      "brand:wikipedia": "en:Lukoil",
      "name": "Lukoil"
    }
  },
  "amenity/fuel|MEROIL": {
    "count": 63,
    "countryCodes": ["es"],
    "match": ["amenity/fuel|Meroil"],
    "tags": {
      "amenity": "fuel",
      "brand": "MEROIL",
      "brand:wikidata": "Q62292559",
      "name": "MEROIL"
    }
  },
  "amenity/fuel|MOL": {
    "count": 504,
    "match": ["amenity/fuel|Mol"],
    "tags": {
      "amenity": "fuel",
      "brand": "MOL",
      "brand:wikidata": "Q549181",
      "brand:wikipedia": "en:MOL (company)",
      "name": "MOL"
    }
  },
  "amenity/fuel|MRS": {
    "count": 70,
    "countryCodes": ["ng"],
    "tags": {
      "amenity": "fuel",
      "brand": "MRS",
      "brand:wikidata": "Q56274919",
      "brand:wikipedia": "en:MRS Oil Nigeria Plc",
      "name": "MRS"
    }
  },
  "amenity/fuel|Mac's": {
    "count": 57,
    "countryCodes": ["ca"],
    "nomatch": ["shop/convenience|Mac's"],
    "tags": {
      "amenity": "fuel",
      "brand": "Mac's",
      "brand:wikidata": "Q4043527",
      "brand:wikipedia": "en:Mac's Convenience Stores",
      "name": "Mac's"
    }
  },
  "amenity/fuel|MacEwen": {
    "count": 68,
    "countryCodes": ["ca"],
    "tags": {
      "amenity": "fuel",
      "brand": "MacEwen",
      "brand:wikidata": "Q61740335",
      "name": "MacEwen"
    }
  },
  "amenity/fuel|Marathon": {
    "count": 1040,
    "nomatch": ["shop/convenience|Marathon"],
    "tags": {
      "amenity": "fuel",
      "brand": "Marathon",
      "brand:wikidata": "Q458363",
      "brand:wikipedia": "en:Marathon Petroleum",
      "name": "Marathon"
    }
  },
  "amenity/fuel|Maverik": {
    "count": 105,
    "countryCodes": ["us"],
    "nomatch": ["shop/convenience|Maverik"],
    "tags": {
      "amenity": "fuel",
      "brand": "Maverik",
      "brand:wikidata": "Q16974822",
      "brand:wikipedia": "en:FJ Management",
      "name": "Maverik"
    }
  },
  "amenity/fuel|Maxol": {
    "count": 71,
    "tags": {
      "amenity": "fuel",
      "brand": "Maxol",
      "brand:wikidata": "Q3302837",
      "brand:wikipedia": "en:Maxol",
      "name": "Maxol"
    }
  },
  "amenity/fuel|Metano": {
    "count": 228,
    "countryCodes": ["it"],
    "tags": {
      "amenity": "fuel",
      "brand": "Metano",
      "brand:wikidata": "Q62294765",
      "name": "Metano"
    }
  },
  "amenity/fuel|Migrol": {
    "count": 85,
    "countryCodes": ["ch"],
    "tags": {
      "amenity": "fuel",
      "brand": "Migrol",
      "brand:wikidata": "Q1747771",
      "brand:wikipedia": "de:Migrol",
      "name": "Migrol"
    }
  },
  "amenity/fuel|Mobil": {
    "count": 1863,
    "match": ["amenity/fuel|Mobile"],
    "nomatch": ["shop/convenience|Mobil Mart"],
    "tags": {
      "amenity": "fuel",
      "brand": "Mobil",
      "brand:wikidata": "Q3088656",
      "brand:wikipedia": "en:Mobil",
      "name": "Mobil"
    }
  },
  "amenity/fuel|Moil": {
    "count": 53,
    "countryCodes": ["tr"],
    "tags": {
      "amenity": "fuel",
      "brand": "Moil",
      "brand:wikidata": "Q62296914",
      "name": "Moil"
    }
  },
  "amenity/fuel|Morrisons": {
    "count": 145,
    "countryCodes": ["gb"],
    "nomatch": ["shop/supermarket|Morrisons"],
    "tags": {
      "amenity": "fuel",
      "brand": "Morrisons",
      "brand:wikidata": "Q922344",
      "brand:wikipedia": "en:Morrisons",
      "name": "Morrisons"
    }
  },
  "amenity/fuel|Moya": {
    "count": 90,
    "countryCodes": ["pl"],
    "tags": {
      "amenity": "fuel",
      "brand": "Moya",
      "brand:wikidata": "Q62297700",
      "name": "Moya"
    }
  },
  "amenity/fuel|Murphy USA": {
    "count": 302,
    "tags": {
      "amenity": "fuel",
      "brand": "Murphy USA",
      "brand:wikidata": "Q19604459",
      "brand:wikipedia": "en:Murphy USA",
      "name": "Murphy USA"
    }
  },
  "amenity/fuel|N1": {
    "count": 56,
    "tags": {
      "amenity": "fuel",
      "brand": "N1",
      "name": "N1"
    }
  },
  "amenity/fuel|NP": {
    "count": 60,
    "tags": {
      "amenity": "fuel",
      "brand": "NP",
      "brand:wikidata": "Q7842382",
      "brand:wikipedia": "en:Trinidad & Tobago National Petroleum Marketing Company Limited",
      "name": "NP"
    }
  },
  "amenity/fuel|Neste": {
    "count": 190,
    "tags": {
      "amenity": "fuel",
      "brand": "Neste",
      "brand:wikidata": "Q616376",
      "brand:wikipedia": "en:Neste",
      "name": "Neste"
    }
  },
  "amenity/fuel|OIL!": {
    "count": 133,
    "tags": {
      "amenity": "fuel",
      "brand": "OIL!",
      "brand:wikidata": "Q2007561",
      "brand:wikipedia": "de:OIL! Tankstellen",
      "name": "OIL!"
    }
  },
  "amenity/fuel|OK": {
    "count": 485,
    "countryCodes": ["dk"],
    "tags": {
      "amenity": "fuel",
      "brand": "OK",
      "brand:wikidata": "Q12329785",
      "brand:wikipedia": "da:OK a.m.b.a.",
      "name": "OK"
    }
  },
  "amenity/fuel|OKQ8": {
    "count": 326,
    "tags": {
      "amenity": "fuel",
      "brand": "OKQ8",
      "brand:wikidata": "Q1634762",
      "brand:wikipedia": "en:Kuwait Petroleum Corporation",
      "name": "OKQ8"
    }
  },
  "amenity/fuel|OMV": {
    "count": 962,
    "tags": {
      "amenity": "fuel",
      "brand": "OMV",
      "brand:wikidata": "Q168238",
      "brand:wikipedia": "en:OMV",
      "name": "OMV"
    }
  },
  "amenity/fuel|Oilibya": {
    "count": 217,
    "match": [
      "amenity/fuel|OLIBYA",
      "amenity/fuel|OLYBIA",
      "amenity/fuel|OiLibya",
      "amenity/fuel|Oil Liby",
      "amenity/fuel|Oil Lybia",
      "amenity/fuel|OilLibia",
      "amenity/fuel|OilLibya",
      "amenity/fuel|OilLybia",
      "amenity/fuel|Oilibia",
      "amenity/fuel|Oilibiya",
      "amenity/fuel|Oilybia"
    ],
    "tags": {
      "amenity": "fuel",
      "brand": "Oilibya",
      "brand:wikidata": "Q7081491",
      "brand:wikipedia": "en:Oilibya",
      "name": "Oilibya",
      "name:ar": "أويليبيا"
    }
  },
  "amenity/fuel|Olerex": {
    "count": 54,
    "tags": {
      "amenity": "fuel",
      "brand": "Olerex",
      "name": "Olerex"
    }
  },
  "amenity/fuel|Opet": {
    "count": 119,
    "countryCodes": ["tr"],
    "tags": {
      "amenity": "fuel",
      "brand": "Opet",
      "brand:wikidata": "Q7072824",
      "brand:wikipedia": "en:Opet",
      "name": "Opet"
    }
  },
  "amenity/fuel|Orlen": {
    "count": 1346,
    "nomatch": ["shop/convenience|Orlen"],
    "tags": {
      "amenity": "fuel",
      "brand": "Orlen",
      "brand:wikidata": "Q971649",
      "brand:wikipedia": "en:PKN Orlen",
      "name": "Orlen"
    }
  },
  "amenity/fuel|Oxxo": {
    "match": ["amenity/fuel|OXXO"],
    "nocount": true,
    "nomatch": ["shop/convenience|Oxxo"],
    "tags": {
      "amenity": "fuel",
      "brand": "Oxxo",
      "brand:wikidata": "Q1342538",
      "brand:wikipedia": "es:Oxxo",
      "name": "Oxxo"
    }
  },
  "amenity/fuel|PSO": {
    "count": 174,
    "match": ["amenity/fuel|PSO Petrol Pump"],
    "tags": {
      "amenity": "fuel",
      "brand": "PSO",
      "brand:wikidata": "Q2741455",
      "brand:wikipedia": "en:Pakistan State Oil",
      "name": "PSO"
    }
  },
  "amenity/fuel|PT": {
    "count": 194,
    "countryCodes": ["th"],
    "match": ["amenity/fuel|P T"],
    "tags": {
      "amenity": "fuel",
      "brand": "PT",
      "brand:wikidata": "Q62298612",
      "name": "PT"
    }
  },
  "amenity/fuel|PTT": {
    "count": 382,
    "match": ["amenity/fuel|P T T"],
    "tags": {
      "amenity": "fuel",
      "brand": "PTT",
      "brand:wikidata": "Q1810389",
      "brand:wikipedia": "en:PTT Public Company Limited",
      "name": "PTT"
    }
  },
  "amenity/fuel|PV Oil": {
    "count": 111,
    "tags": {
      "amenity": "fuel",
      "brand": "PV Oil",
      "brand:wikidata": "Q2089536",
      "brand:wikipedia": "en:Petrovietnam",
      "name": "PV Oil"
    }
  },
  "amenity/fuel|Pacific Pride": {
    "count": 73,
    "countryCodes": ["us"],
    "tags": {
      "amenity": "fuel",
      "brand": "Pacific Pride",
      "brand:wikidata": "Q7122637",
      "brand:wikipedia": "en:Pacific Pride",
      "name": "Pacific Pride"
    }
  },
  "amenity/fuel|Pecsa": {
    "count": 208,
    "countryCodes": ["pe"],
    "tags": {
      "amenity": "fuel",
      "brand": "Pecsa",
      "brand:wikidata": "Q62299262",
      "name": "Pecsa"
    }
  },
  "amenity/fuel|Pemex": {
    "count": 1929,
    "match": ["amenity/fuel|PEMEX"],
    "tags": {
      "amenity": "fuel",
      "brand": "Pemex",
      "brand:wikidata": "Q871308",
      "brand:wikipedia": "en:Pemex",
      "name": "Pemex"
    }
  },
  "amenity/fuel|Pertamina": {
    "count": 314,
    "tags": {
      "amenity": "fuel",
      "brand": "Pertamina",
      "brand:wikidata": "Q1641044",
      "brand:wikipedia": "en:Pertamina",
      "name": "Pertamina"
    }
  },
  "amenity/fuel|Petro": {
    "count": 72,
    "tags": {
      "amenity": "fuel",
      "brand": "Petro",
      "name": "Petro"
    }
  },
  "amenity/fuel|Petro-Canada": {
    "count": 1223,
    "countryCodes": ["ca"],
    "match": ["amenity/fuel|Petro Canada"],
    "nomatch": ["shop/convenience|Petro-Canada"],
    "tags": {
      "amenity": "fuel",
      "brand": "Petro-Canada",
      "brand:wikidata": "Q1208279",
      "brand:wikipedia": "en:Petro-Canada",
      "name": "Petro-Canada"
    }
  },
  "amenity/fuel|Petro-T": {
    "count": 85,
    "tags": {
      "amenity": "fuel",
      "brand": "Petro-T",
      "brand:wikidata": "Q61743540",
      "name": "Petro-T"
    }
  },
  "amenity/fuel|PetroPerú": {
    "count": 61,
    "countryCodes": ["pe"],
    "match": ["amenity/fuel|Petroperu"],
    "tags": {
      "amenity": "fuel",
      "brand": "PetroPerú",
      "brand:wikidata": "Q2506390",
      "brand:wikipedia": "es:Petroperú",
      "name": "PetroPerú"
    }
  },
  "amenity/fuel|Petrochina": {
    "count": 114,
    "countryCodes": ["cn"],
    "tags": {
      "amenity": "fuel",
      "brand": "Petrochina",
      "brand:wikidata": "Q503182",
      "brand:wikipedia": "en:PetroChina",
      "name": "Petrochina"
    }
  },
  "amenity/fuel|Petroecuador": {
    "count": 78,
    "tags": {
      "amenity": "fuel",
      "brand": "Petroecuador",
      "brand:wikidata": "Q1812822",
      "brand:wikipedia": "en:Petroecuador",
      "name": "Petroecuador"
    }
  },
  "amenity/fuel|Petrol Ofisi": {
    "count": 366,
    "tags": {
      "amenity": "fuel",
      "brand": "Petrol Ofisi",
      "brand:wikidata": "Q1278087",
      "brand:wikipedia": "en:Petrol Ofisi",
      "name": "Petrol Ofisi"
    }
  },
  "amenity/fuel|Petrolimex": {
    "count": 365,
    "tags": {
      "amenity": "fuel",
      "brand": "Petrolimex",
      "brand:wikidata": "Q10831598",
      "brand:wikipedia": "en:Petrolimex",
      "name": "Petrolimex"
    }
  },
  "amenity/fuel|Petrolina": {
    "count": 56,
    "countryCodes": ["cy"],
    "tags": {
      "amenity": "fuel",
      "brand": "Petrolina",
      "brand:wikidata": "Q17013948",
      "brand:wikipedia": "en:Petrolina (company)",
      "name": "Petrolina"
    }
  },
  "amenity/fuel|Petrom": {
    "count": 474,
    "tags": {
      "amenity": "fuel",
      "brand": "Petrom",
      "brand:wikidata": "Q1755034",
      "brand:wikipedia": "en:Petrom",
      "name": "Petrom"
    }
  },
  "amenity/fuel|Petron": {
    "count": 1648,
    "countryCodes": ["ph"],
    "tags": {
      "amenity": "fuel",
      "brand": "Petron",
      "brand:wikidata": "Q7179011",
      "brand:wikipedia": "en:Petron Corporation",
      "name": "Petron"
    }
  },
  "amenity/fuel|Petronas": {
    "count": 445,
    "tags": {
      "amenity": "fuel",
      "brand": "Petronas",
      "brand:wikidata": "Q221692",
      "brand:wikipedia": "en:Petronas",
      "name": "Petronas"
    }
  },
  "amenity/fuel|Petronor": {
    "count": 82,
    "match": ["amenity/fuel|PETRONOR"],
    "tags": {
      "amenity": "fuel",
      "brand": "Petronor",
      "brand:wikidata": "Q1726547",
      "brand:wikipedia": "es:Petronor",
      "name": "Petronor"
    }
  },
  "amenity/fuel|Phillips 66": {
    "count": 539,
    "tags": {
      "amenity": "fuel",
      "brand": "Phillips 66",
      "brand:wikidata": "Q1656230",
      "brand:wikipedia": "en:Phillips 66",
      "name": "Phillips 66"
    }
  },
  "amenity/fuel|Phoenix": {
    "count": 225,
    "countryCodes": ["ph"],
    "tags": {
      "amenity": "fuel",
      "brand": "Phoenix",
      "brand:wikidata": "Q7186949",
      "brand:wikipedia": "en:Phoenix Petroleum",
      "name": "Phoenix"
    }
  },
  "amenity/fuel|Pilot": {
    "count": 125,
    "countryCodes": ["ca", "us"],
    "match": [
      "amenity/fuel|Flying J",
      "amenity/fuel|Pilot Flying J"
    ],
    "tags": {
      "amenity": "fuel",
      "brand": "Pilot",
      "brand:wikidata": "Q1434601",
      "brand:wikipedia": "en:Pilot Flying J",
      "name": "Pilot"
    }
  },
  "amenity/fuel|Pioneer": {
    "count": 140,
    "countryCodes": ["ca"],
    "tags": {
      "amenity": "fuel",
      "brand": "Pioneer",
      "brand:wikidata": "Q7196684",
      "brand:wikipedia": "en:Pioneer Energy",
      "name": "Pioneer"
    }
  },
  "amenity/fuel|Preem": {
    "count": 267,
    "tags": {
      "amenity": "fuel",
      "brand": "Preem",
      "brand:wikidata": "Q598835",
      "brand:wikipedia": "en:Preem",
      "name": "Preem"
    }
  },
  "amenity/fuel|Primax~(Ecuador)": {
    "countryCodes": ["ec"],
    "nocount": true,
    "tags": {
      "amenity": "fuel",
      "brand": "Primax",
      "brand:wikidata": "Q62332857",
      "name": "Primax"
    }
  },
  "amenity/fuel|Primax~(Peru)": {
    "countryCodes": ["pe"],
    "nocount": true,
    "tags": {
      "amenity": "fuel",
      "brand": "Primax",
      "brand:wikidata": "Q62332638",
      "name": "Primax"
    }
  },
  "amenity/fuel|Prio": {
    "count": 77,
    "countryCodes": ["pt"],
    "tags": {
      "amenity": "fuel",
      "brand": "Prio",
      "brand:wikidata": "Q62530421",
      "name": "Prio"
    }
  },
  "amenity/fuel|Puma": {
    "count": 654,
    "nomatch": ["shop/clothes|Puma"],
    "tags": {
      "amenity": "fuel",
      "brand": "Puma",
      "brand:wikidata": "Q7259769",
      "brand:wikipedia": "en:Puma Energy",
      "name": "Puma"
    }
  },
  "amenity/fuel|Q1": {
    "count": 56,
    "countryCodes": ["de"],
    "tags": {
      "amenity": "fuel",
      "brand": "Q1",
      "brand:wikidata": "Q62086498",
      "name": "Q1",
      "operator": "Q1 Energie AG",
      "operator:wikidata": "Q2121146",
      "operator:wikipedia": "de:Q1 Energie"
    }
  },
  "amenity/fuel|Q8": {
    "count": 1620,
    "tags": {
      "amenity": "fuel",
      "brand": "Q8",
      "brand:wikidata": "Q1634762",
      "brand:wikipedia": "en:Kuwait Petroleum Corporation",
      "name": "Q8"
    }
  },
  "amenity/fuel|Q8 Easy": {
    "count": 92,
    "tags": {
      "amenity": "fuel",
      "brand": "Q8 Easy",
      "brand:wikidata": "Q1806948",
      "brand:wikipedia": "nl:Q8 Easy",
      "name": "Q8 Easy"
    }
  },
  "amenity/fuel|QT": {
    "count": 52,
    "countryCodes": ["us"],
    "tags": {
      "amenity": "fuel",
      "brand": "QT",
      "brand:wikidata": "Q7271953",
      "brand:wikipedia": "en:QuikTrip",
      "name": "QT"
    }
  },
  "amenity/fuel|Qstar": {
    "count": 121,
    "countryCodes": ["se"],
    "tags": {
      "amenity": "fuel",
      "brand": "Qstar",
      "brand:wikidata": "Q10647961",
      "brand:wikipedia": "sv:Qstar",
      "name": "Qstar"
    }
  },
  "amenity/fuel|QuikTrip": {
    "count": 327,
    "nomatch": ["shop/convenience|QuikTrip"],
    "tags": {
      "amenity": "fuel",
      "brand": "QuikTrip",
      "brand:wikidata": "Q7271953",
      "brand:wikipedia": "en:QuikTrip",
      "name": "QuikTrip"
    }
  },
  "amenity/fuel|Race Trac": {
    "count": 62,
    "match": ["amenity/fuel|RaceTrac"],
    "tags": {
      "amenity": "fuel",
      "brand": "Race Trac",
      "brand:wikidata": "Q735942",
      "brand:wikipedia": "en:RaceTrac",
      "name": "Race Trac"
    }
  },
  "amenity/fuel|Raiffeisen": {
    "count": 133,
    "nomatch": ["amenity/bank|Raiffeisenbank"],
    "tags": {
      "amenity": "fuel",
      "brand": "Raiffeisen",
      "name": "Raiffeisen"
    }
  },
  "amenity/fuel|Repsol": {
    "count": 1527,
    "match": ["amenity/fuel|REPSOL"],
    "tags": {
      "amenity": "fuel",
      "brand": "Repsol",
      "brand:wikidata": "Q174747",
      "brand:wikipedia": "es:Repsol",
      "name": "Repsol"
    }
  },
  "amenity/fuel|Revoil": {
    "count": 72,
    "countryCodes": ["gr"],
    "tags": {
      "amenity": "fuel",
      "brand": "Revoil",
      "brand:wikidata": "Q62530755",
      "name": "Revoil"
    }
  },
  "amenity/fuel|Rompetrol": {
    "count": 258,
    "tags": {
      "amenity": "fuel",
      "brand": "Rompetrol",
      "brand:wikidata": "Q1788862",
      "brand:wikipedia": "en:Rompetrol",
      "name": "Rompetrol"
    }
  },
  "amenity/fuel|Royal Farms": {
    "count": 96,
    "countryCodes": ["us"],
    "nomatch": ["shop/convenience|Royal Farms"],
    "tags": {
      "amenity": "fuel",
      "brand": "Royal Farms",
      "brand:wikidata": "Q7374169",
      "brand:wikipedia": "en:Royal Farms",
      "name": "Royal Farms"
    }
  },
  "amenity/fuel|Rubis": {
    "count": 111,
    "tags": {
      "amenity": "fuel",
      "brand": "Rubis",
      "brand:wikidata": "Q3446514",
      "brand:wikipedia": "en:Rubis (company)",
      "name": "Rubis"
    }
  },
  "amenity/fuel|SK주유소": {
    "count": 54,
    "countryCodes": ["kr"],
    "tags": {
      "amenity": "fuel",
      "brand": "SK주유소",
      "brand:ko": "SK주유소",
      "name": "SK주유소",
      "name:ko": "SK주유소"
    }
  },
  "amenity/fuel|SP": {
    "count": 56,
    "tags": {
      "amenity": "fuel",
      "brand": "SP",
      "name": "SP"
    }
  },
  "amenity/fuel|Safeway": {
    "count": 98,
    "nomatch": ["shop/supermarket|Safeway"],
    "tags": {
      "amenity": "fuel",
      "brand": "Safeway",
      "brand:wikidata": "Q1508234",
      "brand:wikipedia": "en:Safeway Inc.",
      "name": "Safeway"
    }
  },
  "amenity/fuel|Sainsbury's": {
    "count": 87,
    "countryCodes": ["gb"],
    "match": ["amenity/fuel|Sainsburys"],
    "nomatch": ["shop/supermarket|Sainsbury's"],
    "tags": {
      "amenity": "fuel",
      "brand": "Sainsbury's",
      "brand:wikidata": "Q152096",
      "brand:wikipedia": "en:Sainsbury's",
      "name": "Sainsbury's"
    }
  },
  "amenity/fuel|Sam's Club": {
    "count": 80,
    "nomatch": ["shop/wholesale|Sam's Club"],
    "tags": {
      "amenity": "fuel",
      "brand": "Sam's Club",
      "brand:wikidata": "Q1972120",
      "brand:wikipedia": "en:Sam's Club",
      "name": "Sam's Club",
      "operator": "Walmart",
      "operator:wikidata": "Q483551",
      "operator:wikipedia": "en:Walmart"
    }
  },
  "amenity/fuel|Sasol": {
    "count": 134,
    "tags": {
      "amenity": "fuel",
      "brand": "Sasol",
      "brand:wikidata": "Q905998",
      "brand:wikipedia": "en:Sasol",
      "name": "Sasol"
    }
  },
  "amenity/fuel|Sea Oil": {
    "count": 95,
    "countryCodes": ["ph"],
    "match": ["amenity/fuel|Seaoil"],
    "tags": {
      "amenity": "fuel",
      "brand": "Sea Oil",
      "brand:wikidata": "Q7389549",
      "brand:wikipedia": "en:Seaoil Philippines",
      "name": "Sea Oil"
    }
  },
  "amenity/fuel|Sheetz": {
    "count": 410,
    "nomatch": ["shop/convenience|Sheetz"],
    "tags": {
      "amenity": "fuel",
      "brand": "Sheetz",
      "brand:wikidata": "Q7492551",
      "brand:wikipedia": "en:Sheetz",
      "name": "Sheetz"
    }
  },
  "amenity/fuel|Shell": {
    "count": 14330,
    "match": [
      "amenity/fuel|Posto Shell",
      "amenity/fuel|SHELL",
      "amenity/fuel|Shell Gas Station",
      "amenity/fuel|Shell Petrol Station",
      "amenity/fuel|Shell Station",
      "amenity/fuel|Station Shell",
      "amenity/fuel|shell"
    ],
    "nomatch": [
      "amenity/fuel|Shell Express",
      "shop/convenience|Shell Select"
    ],
    "tags": {
      "amenity": "fuel",
      "brand": "Shell",
      "brand:wikidata": "Q154950",
      "brand:wikipedia": "en:Royal Dutch Shell",
      "name": "Shell"
    }
  },
  "amenity/fuel|Shell Express": {
    "count": 137,
    "nomatch": [
      "amenity/fuel|Shell",
      "shop/convenience|Shell Select"
    ],
    "tags": {
      "amenity": "fuel",
      "brand": "Shell Express",
      "brand:wikidata": "Q2289188",
      "brand:wikipedia": "nl:Shell Express",
      "name": "Shell Express"
    }
  },
  "amenity/fuel|Sinclair": {
    "count": 256,
    "countryCodes": ["us"],
    "tags": {
      "amenity": "fuel",
      "brand": "Sinclair",
      "brand:wikidata": "Q1290900",
      "brand:wikipedia": "en:Sinclair Oil Corporation",
      "name": "Sinclair"
    }
  },
  "amenity/fuel|Sinopec": {
    "count": 130,
    "countryCodes": ["cn"],
    "match": ["amenity/fuel|Sinopec Fuel"],
    "tags": {
      "amenity": "fuel",
      "brand": "Sinopec",
      "brand:wikidata": "Q831445",
      "brand:wikipedia": "en:Sinopec",
      "brand:zh": "中国石化",
      "name": "Sinopec",
      "name:zh": "中国石化"
    }
  },
  "amenity/fuel|Slovnaft": {
    "count": 243,
    "tags": {
      "amenity": "fuel",
      "brand": "Slovnaft",
      "brand:wikidata": "Q1587563",
      "brand:wikipedia": "en:Slovnaft",
      "name": "Slovnaft"
    }
  },
  "amenity/fuel|Socar": {
    "count": 113,
    "tags": {
      "amenity": "fuel",
      "brand": "Socar",
      "brand:wikidata": "Q1622293",
      "brand:wikipedia": "en:SOCAR",
      "name": "Socar"
    }
  },
  "amenity/fuel|Sokimex": {
    "count": 87,
    "tags": {
      "amenity": "fuel",
      "brand": "Sokimex",
      "brand:wikidata": "Q1149575",
      "brand:wikipedia": "en:Sokimex",
      "name": "Sokimex"
    }
  },
  "amenity/fuel|Sonic": {
    "count": 126,
    "nomatch": ["amenity/fast_food|Sonic"],
    "tags": {
      "amenity": "fuel",
      "brand": "Sonic",
      "name": "Sonic"
    }
  },
  "amenity/fuel|Speedway": {
    "count": 885,
    "nomatch": ["shop/convenience|Speedway"],
    "tags": {
      "amenity": "fuel",
      "brand": "Speedway",
      "brand:wikidata": "Q7575683",
      "brand:wikipedia": "en:Speedway LLC",
      "name": "Speedway"
    }
  },
  "amenity/fuel|Sprint": {
    "count": 54,
    "countryCodes": ["de"],
    "nomatch": ["shop/mobile_phone|Sprint"],
    "tags": {
      "amenity": "fuel",
      "brand": "Sprint",
      "brand:wikidata": "Q57588452",
      "name": "Sprint"
    }
  },
  "amenity/fuel|St1": {
    "count": 222,
    "tags": {
      "amenity": "fuel",
      "brand": "St1",
      "brand:wikidata": "Q7592214",
      "brand:wikipedia": "en:St1",
      "name": "St1"
    }
  },
  "amenity/fuel|Star": {
    "count": 440,
    "countryCodes": ["de"],
    "tags": {
      "amenity": "fuel",
      "brand": "Star",
      "brand:wikidata": "Q2031095",
      "brand:wikipedia": "de:Orlen Deutschland",
      "name": "Star"
    }
  },
  "amenity/fuel|Star Oil": {
    "count": 136,
    "tags": {
      "amenity": "fuel",
      "brand": "Star Oil",
      "name": "Star Oil"
    }
  },
  "amenity/fuel|Station Service E. Leclerc": {
    "count": 400,
    "match": [
      "amenity/fuel|E. Leclerc",
      "shop/gas|Station Service E. Leclerc"
    ],
    "tags": {
      "amenity": "fuel",
      "brand": "E.Leclerc",
      "brand:wikidata": "Q1273376",
      "brand:wikipedia": "fr:E.Leclerc",
      "name": "Station Service E. Leclerc"
    }
  },
  "amenity/fuel|Statoil": {
    "count": 209,
    "tags": {
      "amenity": "fuel",
      "brand": "Statoil",
      "brand:wikidata": "Q1776022",
      "brand:wikipedia": "en:Equinor",
      "name": "Statoil"
    }
  },
  "amenity/fuel|Stewart's": {
    "count": 79,
    "countryCodes": ["us"],
    "nomatch": ["shop/convenience|Stewart's"],
    "tags": {
      "amenity": "fuel",
      "brand": "Stewart's",
      "brand:wikidata": "Q7615690",
      "brand:wikipedia": "en:Stewart's Shops",
      "name": "Stewart's"
    }
  },
  "amenity/fuel|Sunoco": {
    "count": 1205,
    "nomatch": ["shop/convenience|Sunoco"],
    "tags": {
      "amenity": "fuel",
      "brand": "Sunoco",
      "brand:wikidata": "Q1423218",
      "brand:wikipedia": "en:Sunoco",
      "name": "Sunoco"
    }
  },
  "amenity/fuel|Super U": {
    "count": 190,
    "countryCodes": ["fr"],
    "nomatch": [
      "shop/convenience|Utile",
      "shop/supermarket|Hyper U",
      "shop/supermarket|Super U",
      "shop/supermarket|U Express"
    ],
    "tags": {
      "amenity": "fuel",
      "brand": "Super U",
      "brand:wikidata": "Q2529029",
      "brand:wikipedia": "en:Système U",
      "name": "Super U"
    }
  },
  "amenity/fuel|Susco": {
    "count": 55,
    "tags": {
      "amenity": "fuel",
      "brand": "Susco",
      "name": "Susco"
    }
  },
  "amenity/fuel|Tamoil": {
    "count": 967,
    "tags": {
      "amenity": "fuel",
      "brand": "Tamoil",
      "brand:wikidata": "Q706793",
      "brand:wikipedia": "en:Tamoil",
      "name": "Tamoil"
    }
  },
  "amenity/fuel|Tango": {
    "count": 151,
    "tags": {
      "amenity": "fuel",
      "brand": "Tango",
      "brand:wikidata": "Q2423920",
      "brand:wikipedia": "nl:Tango CV",
      "name": "Tango"
    }
  },
  "amenity/fuel|Tanka": {
    "count": 51,
    "countryCodes": ["se"],
    "tags": {
      "amenity": "fuel",
      "brand": "Tanka",
      "brand:wikidata": "Q10690640",
      "brand:wikipedia": "sv:Tanka (bensinstationskedja)",
      "name": "Tanka"
    }
  },
  "amenity/fuel|Teboil": {
    "count": 95,
    "tags": {
      "amenity": "fuel",
      "brand": "Teboil",
      "brand:wikidata": "Q7692079",
      "brand:wikipedia": "en:Teboil",
      "name": "Teboil"
    }
  },
  "amenity/fuel|Tela": {
    "count": 217,
    "countryCodes": ["kh"],
    "tags": {
      "amenity": "fuel",
      "brand": "Tela",
      "brand:wikidata": "Q62534875",
      "name": "Tela"
    }
  },
  "amenity/fuel|Tempo": {
    "count": 81,
    "countryCodes": ["ca"],
    "tags": {
      "amenity": "fuel",
      "brand": "Tempo",
      "brand:wikidata": "Q62535175",
      "name": "Tempo"
    }
  },
  "amenity/fuel|Terpel": {
    "count": 552,
    "tags": {
      "amenity": "fuel",
      "brand": "Terpel",
      "brand:wikidata": "Q7703003",
      "brand:wikipedia": "en:Terpel",
      "name": "Terpel"
    }
  },
  "amenity/fuel|Tesco": {
    "count": 229,
    "nomatch": ["shop/convenience|Tesco"],
    "tags": {
      "amenity": "fuel",
      "brand": "Tesco",
      "brand:wikidata": "Q17145596",
      "brand:wikipedia": "en:Tesco Corporation",
      "name": "Tesco"
    }
  },
  "amenity/fuel|Texaco": {
    "count": 1347,
    "nomatch": ["shop/convenience|Texaco"],
    "tags": {
      "amenity": "fuel",
      "brand": "Texaco",
      "brand:wikidata": "Q775060",
      "brand:wikipedia": "en:Texaco",
      "name": "Texaco"
    }
  },
  "amenity/fuel|Tinq": {
    "count": 225,
    "countryCodes": ["nl"],
    "tags": {
      "amenity": "fuel",
      "brand": "Tinq",
      "brand:wikidata": "Q2132028",
      "brand:wikipedia": "nl:Tinq",
      "name": "Tinq"
    }
  },
  "amenity/fuel|Topaz": {
    "count": 116,
    "countryCodes": ["ie"],
    "tags": {
      "amenity": "fuel",
      "brand": "Topaz",
      "brand:wikidata": "Q7824764",
      "brand:wikipedia": "en:Topaz Energy",
      "name": "Topaz"
    }
  },
  "amenity/fuel|Total": {
    "count": 3649,
    "match": [
      "amenity/fuel|Station Total",
      "amenity/fuel|TOTAL"
    ],
    "nomatch": ["shop/convenience|Total"],
    "tags": {
      "amenity": "fuel",
      "brand": "Total",
      "brand:wikidata": "Q154037",
      "brand:wikipedia": "fr:Total (entreprise)",
      "name": "Total"
    }
  },
  "amenity/fuel|Total Access": {
    "count": 262,
    "tags": {
      "amenity": "fuel",
      "brand": "Total Access",
      "brand:wikidata": "Q154037",
      "brand:wikipedia": "fr:Total (entreprise)",
      "name": "Total Access"
    }
  },
  "amenity/fuel|TotalErg": {
    "count": 355,
    "match": ["amenity/fuel|Total Erg"],
    "tags": {
      "amenity": "fuel",
      "brand": "TotalErg",
      "brand:wikidata": "Q3995933",
      "brand:wikipedia": "it:TotalErg",
      "name": "TotalErg"
    }
  },
  "amenity/fuel|Turkey Hill": {
    "count": 119,
    "countryCodes": ["us"],
    "nomatch": ["shop/convenience|Turkey Hill"],
    "tags": {
      "amenity": "fuel",
      "brand": "Turkey Hill",
      "brand:wikidata": "Q42376970",
      "brand:wikipedia": "en:Turkey Hill Minit Markets",
      "name": "Turkey Hill"
    }
  },
  "amenity/fuel|Turmöl": {
    "count": 87,
    "tags": {
      "amenity": "fuel",
      "brand": "Turmöl",
      "brand:wikidata": "Q1473279",
      "brand:wikipedia": "de:Turmöl",
      "name": "Turmöl"
    }
  },
  "amenity/fuel|UDF Fuel": {
    "countryCodes": ["us"],
    "match": [
      "amenity/fuel|UDF",
      "amenity/fuel|UDF Fuels",
      "amenity/fuel|United Dairy Farmers"
    ],
    "nocount": true,
    "nomatch": [
      "shop/convenience|United Dairy Farmers"
    ],
    "tags": {
      "amenity": "fuel",
      "brand": "United Dairy Farmers",
      "brand:wikidata": "Q7887677",
      "brand:wikipedia": "en:United Dairy Farmers",
      "name": "UDF Fuel",
      "short_name": "UDF"
    }
  },
  "amenity/fuel|Ultramar": {
    "count": 628,
    "nomatch": ["shop/convenience|Ultramar"],
    "tags": {
      "amenity": "fuel",
      "brand": "Ultramar",
      "brand:wikidata": "Q3548078",
      "brand:wikipedia": "en:Ultramar",
      "name": "Ultramar"
    }
  },
  "amenity/fuel|United": {
    "count": 217,
    "match": ["amenity/fuel|United Petroleum"],
    "nomatch": ["amenity/bank|United Bank"],
    "tags": {
      "amenity": "fuel",
      "brand": "United",
      "brand:wikidata": "Q28224393",
      "brand:wikipedia": "en:United Petroleum",
      "name": "United"
    }
  },
  "amenity/fuel|Uno": {
    "count": 160,
    "countryCodes": [
      "bz",
      "cr",
      "gt",
      "hn",
      "ni",
      "sv"
    ],
    "tags": {
      "amenity": "fuel",
      "brand": "Uno",
      "brand:wikidata": "Q62535574",
      "name": "Uno"
    }
  },
  "amenity/fuel|Uno-X": {
    "count": 114,
    "countryCodes": ["dk"],
    "tags": {
      "amenity": "fuel",
      "brand": "Uno-X",
      "brand:wikidata": "Q3362746",
      "brand:wikipedia": "en:Uno-X",
      "name": "Uno-X"
    }
  },
  "amenity/fuel|Valero": {
    "count": 1055,
    "nomatch": ["shop/convenience|Valero"],
    "tags": {
      "amenity": "fuel",
      "brand": "Valero",
      "brand:wikidata": "Q1283291",
      "brand:wikipedia": "en:Valero Energy",
      "name": "Valero"
    }
  },
  "amenity/fuel|Viada": {
    "count": 79,
    "tags": {
      "amenity": "fuel",
      "brand": "Viada",
      "brand:wikidata": "Q12663942",
      "brand:wikipedia": "en:Lukoil Baltija",
      "name": "Viada"
    }
  },
  "amenity/fuel|Vito": {
    "count": 100,
    "countryCodes": ["fr"],
    "tags": {
      "amenity": "fuel",
      "brand": "Vito",
      "brand:wikidata": "Q62536473",
      "name": "Vito"
    }
  },
  "amenity/fuel|WOG": {
    "count": 347,
    "tags": {
      "amenity": "fuel",
      "brand": "WOG",
      "brand:wikidata": "Q12072939",
      "brand:wikipedia": "en:WOG (gas stations)",
      "name": "WOG"
    }
  },
  "amenity/fuel|Wawa": {
    "count": 261,
    "nomatch": ["shop/convenience|Wawa"],
    "tags": {
      "amenity": "fuel",
      "brand": "Wawa",
      "brand:wikidata": "Q5936320",
      "brand:wikipedia": "en:Wawa (company)",
      "name": "Wawa"
    }
  },
  "amenity/fuel|Westfalen": {
    "count": 93,
    "countryCodes": ["de"],
    "tags": {
      "amenity": "fuel",
      "brand": "Westfalen",
      "brand:wikidata": "Q1411209",
      "brand:wikipedia": "en:Westfalen AG",
      "name": "Westfalen"
    }
  },
  "amenity/fuel|Woolworths Petrol": {
    "count": 214,
    "countryCodes": ["au"],
    "nomatch": [
      "shop/convenience|Woolworths Petrol"
    ],
    "tags": {
      "amenity": "fuel",
      "brand": "Caltex",
      "brand:wikidata": "Q5023980",
      "brand:wikipedia": "en:Caltex Woolworths",
      "name": "Woolworths Petrol"
    }
  },
  "amenity/fuel|XTR": {
    "count": 99,
    "countryCodes": ["ca"],
    "tags": {
      "amenity": "fuel",
      "brand": "XTR",
      "brand:wikidata": "Q62537250",
      "name": "XTR"
    }
  },
  "amenity/fuel|YPF": {
    "count": 323,
    "tags": {
      "amenity": "fuel",
      "brand": "YPF",
      "brand:wikidata": "Q2006989",
      "brand:wikipedia": "en:YPF",
      "name": "YPF"
    }
  },
  "amenity/fuel|Z": {
    "count": 100,
    "countryCodes": ["nz"],
    "tags": {
      "amenity": "fuel",
      "brand": "Z",
      "brand:wikidata": "Q8063337",
      "brand:wikipedia": "en:Z Energy",
      "name": "Z"
    }
  },
  "amenity/fuel|bft": {
    "count": 223,
    "countryCodes": ["de"],
    "match": ["amenity/fuel|BFT"],
    "tags": {
      "amenity": "fuel",
      "brand": "bft",
      "brand:wikidata": "Q1009104",
      "brand:wikipedia": "de:Bundesverband freier Tankstellen",
      "name": "bft"
    }
  },
  "amenity/fuel|din-X": {
    "count": 51,
    "countryCodes": ["se"],
    "tags": {
      "amenity": "fuel",
      "brand": "din-X",
      "brand:wikidata": "Q10472858",
      "brand:wikipedia": "sv:Din-X",
      "name": "din-X"
    }
  },
  "amenity/fuel|Авіас": {
    "count": 131,
    "countryCodes": ["ua"],
    "tags": {
      "amenity": "fuel",
      "brand": "Авіас",
      "brand:wikidata": "Q12122687",
      "brand:wikipedia": "uk:Мережа АЗС Приват",
      "name": "Авіас"
    }
  },
  "amenity/fuel|БРСМ-Нафта": {
    "count": 73,
    "countryCodes": ["ua"],
    "tags": {
      "amenity": "fuel",
      "brand": "БРСМ-Нафта",
      "brand:wikidata": "Q56356523",
      "brand:wikipedia": "uk:БРСМ-Нафта",
      "name": "БРСМ-Нафта"
    }
  },
  "amenity/fuel|Башнефть": {
    "count": 293,
    "countryCodes": ["ru"],
    "tags": {
      "amenity": "fuel",
      "brand": "Башнефть",
      "brand:en": "Bashneft",
      "brand:wikidata": "Q809985",
      "brand:wikipedia": "en:Bashneft",
      "name": "Башнефть",
      "name:en": "Bashneft"
    }
  },
  "amenity/fuel|Белоруснефть": {
    "count": 71,
    "tags": {
      "amenity": "fuel",
      "brand": "Белоруснефть",
      "brand:wikidata": "Q4082693",
      "brand:wikipedia": "ru:Белоруснефть",
      "name": "Белоруснефть"
    }
  },
  "amenity/fuel|Газпромнефть": {
    "count": 1171,
    "match": ["amenity/fuel|Газпром"],
    "tags": {
      "amenity": "fuel",
      "brand": "Газпромнефть",
      "brand:wikidata": "Q1461799",
      "brand:wikipedia": "en:Gazprom Neft",
      "name": "Газпромнефть"
    }
  },
  "amenity/fuel|Гелиос": {
    "count": 83,
    "countryCodes": ["kz"],
    "match": ["amenity/fuel|Helios"],
    "tags": {
      "amenity": "fuel",
      "brand": "Гелиос",
      "brand:en": "Helios",
      "brand:wikidata": "Q62286471",
      "name": "Гелиос",
      "name:en": "Helios"
    }
  },
  "amenity/fuel|ЕКА": {
    "count": 85,
    "countryCodes": ["ru"],
    "tags": {
      "amenity": "fuel",
      "brand": "ЕКА",
      "brand:wikidata": "Q62543029",
      "name": "ЕКА"
    }
  },
  "amenity/fuel|КЛО": {
    "count": 51,
    "countryCodes": ["ua"],
    "tags": {
      "amenity": "fuel",
      "brand": "КЛО",
      "brand:en": "Klo",
      "brand:wikidata": "Q60966526",
      "brand:wikipedia": "ru:КЛО (сеть_АЗС)",
      "name": "КЛО",
      "name:en": "Klo"
    }
  },
  "amenity/fuel|КазМунайГаз": {
    "count": 153,
    "countryCodes": ["kz"],
    "nomatch": ["shop/convenience|КазМунайГаз"],
    "tags": {
      "amenity": "fuel",
      "brand": "КазМунайГаз",
      "brand:wikidata": "Q1417227",
      "brand:wikipedia": "en:KazMunayGas",
      "name": "КазМунайГаз"
    }
  },
  "amenity/fuel|Лукойл": {
    "count": 2363,
    "match": ["amenity/fuel|Лукоил"],
    "nomatch": ["shop/convenience|Лукойл"],
    "tags": {
      "amenity": "fuel",
      "brand": "Лукойл",
      "brand:wikidata": "Q329347",
      "brand:wikipedia": "ru:Лукойл",
      "name": "Лукойл"
    }
  },
  "amenity/fuel|Макпетрол": {
    "count": 108,
    "countryCodes": ["mk"],
    "tags": {
      "amenity": "fuel",
      "brand": "Макпетрол",
      "brand:wikidata": "Q1886438",
      "brand:wikipedia": "en:Makpetrol",
      "name": "Макпетрол"
    }
  },
  "amenity/fuel|НК Альянс": {
    "count": 59,
    "countryCodes": ["ru"],
    "tags": {
      "amenity": "fuel",
      "brand": "НК Альянс",
      "brand:wikidata": "Q4063700",
      "brand:wikipedia": "ru:Альянс (компания)",
      "name": "НК Альянс"
    }
  },
  "amenity/fuel|Нефтьмагистраль": {
    "count": 76,
    "countryCodes": ["ru"],
    "tags": {
      "amenity": "fuel",
      "brand": "Нефтьмагистраль",
      "brand:wikidata": "Q62544323",
      "name": "Нефтьмагистраль"
    }
  },
  "amenity/fuel|ОККО": {
    "count": 328,
    "tags": {
      "amenity": "fuel",
      "brand": "ОККО",
      "brand:en": "OKKO",
      "brand:wikidata": "Q7072617",
      "brand:wikipedia": "en:OKKO",
      "name": "ОККО",
      "name:en": "OKKO"
    }
  },
  "amenity/fuel|ОМВ": {
    "count": 53,
    "countryCodes": ["bg", "rs"],
    "tags": {
      "amenity": "fuel",
      "brand": "ОМВ",
      "brand:wikidata": "Q168238",
      "brand:wikipedia": "en:OMV",
      "name": "ОМВ"
    }
  },
  "amenity/fuel|ПТК": {
    "count": 115,
    "tags": {
      "amenity": "fuel",
      "brand": "ПТК",
      "brand:en": "The Petersburg Fuel Company",
      "brand:wikidata": "Q4360193",
      "brand:wikipedia": "en:Petersburg Fuel Company",
      "name": "ПТК",
      "name:en": "The Petersburg Fuel Company"
    }
  },
  "amenity/fuel|Петрол": {
    "count": 149,
    "countryCodes": ["bg"],
    "tags": {
      "amenity": "fuel",
      "brand": "Петрол",
      "brand:wikidata": "Q24315",
      "brand:wikipedia": "en:Petrol AD",
      "name": "Петрол"
    }
  },
  "amenity/fuel|Роснефть": {
    "count": 1133,
    "tags": {
      "amenity": "fuel",
      "brand": "Роснефть",
      "brand:en": "Rosneft",
      "brand:wikidata": "Q1141123",
      "brand:wikipedia": "en:Rosneft",
      "name": "Роснефть",
      "name:en": "Rosneft"
    }
  },
  "amenity/fuel|Сибнефть": {
    "count": 51,
    "tags": {
      "amenity": "fuel",
      "brand": "Сибнефть",
      "name": "Сибнефть"
    }
  },
  "amenity/fuel|Сургутнефтегаз": {
    "count": 107,
    "tags": {
      "amenity": "fuel",
      "brand": "Сургутнефтегаз",
      "brand:en": "Surgutneftegas",
      "brand:wikidata": "Q680776",
      "brand:wikipedia": "en:Surgutneftegas",
      "name": "Сургутнефтегаз",
      "name:en": "Surgutneftegas"
    }
  },
  "amenity/fuel|ТНК": {
    "count": 478,
    "tags": {
      "amenity": "fuel",
      "brand": "ТНК",
      "brand:wikidata": "Q2298901",
      "brand:wikipedia": "en:TNK-BP",
      "name": "ТНК"
    }
  },
  "amenity/fuel|Татнефтепродукт": {
    "count": 61,
    "countryCodes": ["ru"],
    "tags": {
      "amenity": "fuel",
      "brand": "Татнефтепродукт",
      "name": "Татнефтепродукт",
      "operator": "ТАИФ",
      "operator:wikidata": "Q4448860",
      "operator:wikipedia": "en:ТАИФ"
    }
  },
  "amenity/fuel|Татнефть": {
    "count": 354,
    "tags": {
      "amenity": "fuel",
      "brand": "Татнефть",
      "brand:en": "Tatneft",
      "brand:wikidata": "Q1616858",
      "brand:wikipedia": "en:Tatneft",
      "name": "Татнефть",
      "name:en": "Tatneft"
    }
  },
  "amenity/fuel|Укрнафта": {
    "count": 255,
    "tags": {
      "amenity": "fuel",
      "brand": "Укрнафта",
      "brand:en": "Ukrnafta",
      "brand:wikidata": "Q2447961",
      "brand:wikipedia": "en:Ukrnafta",
      "name": "Укрнафта",
      "name:en": "Ukrnafta"
    }
  },
  "amenity/fuel|דור אלון": {
    "count": 125,
    "countryCodes": ["il"],
    "tags": {
      "amenity": "fuel",
      "brand": "דור אלון",
      "brand:he": "דור אלון",
      "name": "דור אלון",
      "name:he": "דור אלון"
    }
  },
  "amenity/fuel|סונול": {
    "count": 141,
    "countryCodes": ["il"],
    "tags": {
      "amenity": "fuel",
      "brand": "סונול",
      "brand:en": "Sonol",
      "brand:he": "סונול",
      "brand:wikidata": "Q3701622",
      "brand:wikipedia": "en:Sonol",
      "name": "סונול",
      "name:en": "Sonol",
      "name:he": "סונול"
    }
  },
  "amenity/fuel|פז": {
    "count": 191,
    "countryCodes": ["il"],
    "tags": {
      "amenity": "fuel",
      "brand": "פז",
      "brand:he": "פז",
      "brand:wikidata": "Q2211731",
      "brand:wikipedia": "en:Paz Oil Company",
      "name": "פז",
      "name:he": "פז"
    }
  },
  "amenity/fuel|ادنوك": {
    "count": 239,
    "tags": {
      "amenity": "fuel",
      "brand": "ادنوك",
      "name": "ادنوك"
    }
  },
  "amenity/fuel|บางจาก": {
    "count": 222,
    "countryCodes": ["th"],
    "tags": {
      "amenity": "fuel",
      "brand": "บางจาก",
      "brand:th": "บางจาก",
      "brand:wikidata": "Q6579719",
      "brand:wikipedia": "th:บางจาก คอร์ปอเรชัน",
      "name": "บางจาก",
      "name:th": "บางจาก"
    }
  },
  "amenity/fuel|ป.ต.ท.": {
    "count": 407,
    "countryCodes": ["th"],
    "tags": {
      "amenity": "fuel",
      "brand": "ป.ต.ท.",
      "brand:th": "ป.ต.ท.",
      "brand:wikidata": "Q1810389",
      "brand:wikipedia": "th:ปตท.",
      "name": "ป.ต.ท.",
      "name:th": "ป.ต.ท."
    }
  },
  "amenity/fuel|เชลล์": {
    "count": 87,
    "countryCodes": ["th"],
    "tags": {
      "amenity": "fuel",
      "brand": "เชลล์",
      "brand:th": "เชลล์",
      "brand:wikidata": "Q18109",
      "brand:wikipedia": "th:เชลล์",
      "name": "เชลล์",
      "name:th": "เชลล์"
    }
  },
  "amenity/fuel|เอสโซ่": {
    "count": 80,
    "countryCodes": ["th"],
    "tags": {
      "amenity": "fuel",
      "brand": "เอสโซ่",
      "brand:en": "Esso",
      "brand:th": "เอสโซ่",
      "brand:wikidata": "Q867662",
      "brand:wikipedia": "en:Esso",
      "name": "เอสโซ่",
      "name:en": "Esso",
      "name:th": "เอสโซ่"
    }
  },
  "amenity/fuel|エッソ": {
    "count": 128,
    "countryCodes": ["jp"],
    "tags": {
      "amenity": "fuel",
      "brand": "エッソ",
      "brand:en": "Esso",
      "brand:ja": "エッソ",
      "brand:wikidata": "Q867662",
      "brand:wikipedia": "en:Esso",
      "name": "エッソ",
      "name:en": "Esso",
      "name:ja": "エッソ"
    }
  },
  "amenity/fuel|エッソ石油": {
    "count": 62,
    "countryCodes": ["jp"],
    "tags": {
      "amenity": "fuel",
      "brand": "エッソ石油",
      "brand:ja": "エッソ石油",
      "name": "エッソ石油",
      "name:ja": "エッソ石油"
    }
  },
  "amenity/fuel|エネオス": {
    "count": 637,
    "countryCodes": ["jp"],
    "tags": {
      "amenity": "fuel",
      "brand": "エネオス",
      "brand:en": "JXTG Nippon Oil & Energy",
      "brand:ja": "エネオス",
      "brand:wikidata": "Q1640290",
      "brand:wikipedia": "en:JXTG Nippon Oil & Energy",
      "name": "エネオス",
      "name:en": "JXTG Nippon Oil & Energy",
      "name:ja": "エネオス"
    }
  },
  "amenity/fuel|コスモ石油": {
    "count": 602,
    "countryCodes": ["jp"],
    "tags": {
      "amenity": "fuel",
      "brand": "コスモ石油",
      "brand:en": "Cosmo Oil Company",
      "brand:ja": "コスモ石油",
      "brand:wikidata": "Q2498318",
      "brand:wikipedia": "en:Cosmo Oil Company",
      "name": "コスモ石油",
      "name:en": "Cosmo Oil Company",
      "name:ja": "コスモ石油"
    }
  },
  "amenity/fuel|ゼネラル": {
    "count": 93,
    "countryCodes": ["jp"],
    "tags": {
      "amenity": "fuel",
      "brand": "ゼネラル",
      "brand:en": "Tonen General",
      "brand:ja": "ゼネラル",
      "brand:wikidata": "Q11528048",
      "brand:wikipedia": "ja:東燃ゼネラル石油",
      "name": "ゼネラル",
      "name:en": "Tonen General",
      "name:ja": "ゼネラル"
    }
  },
  "amenity/fuel|中国石化": {
    "count": 187,
    "countryCodes": ["cn"],
    "tags": {
      "amenity": "fuel",
      "brand": "中国石化",
      "brand:en": "Sinopec",
      "brand:wikidata": "Q831445",
      "brand:wikipedia": "en:Sinopec",
      "name": "中国石化",
      "name:en": "Sinopec"
    }
  },
  "amenity/fuel|中国石化 Sinopec": {
    "count": 130,
    "countryCodes": ["cn"],
    "tags": {
      "amenity": "fuel",
      "brand": "中国石化 Sinopec",
      "brand:wikidata": "Q831445",
      "brand:wikipedia": "zh:中国石化",
      "name": "中国石化 Sinopec"
    }
  },
  "amenity/fuel|中国石油": {
    "count": 128,
    "tags": {
      "amenity": "fuel",
      "brand": "中国石油",
      "brand:en": "PetroChina",
      "brand:wikidata": "Q503182",
      "brand:wikipedia": "en:PetroChina",
      "name": "中国石油",
      "name:en": "PetroChina"
    }
  },
  "amenity/fuel|出光": {
    "count": 887,
    "countryCodes": ["jp"],
    "tags": {
      "amenity": "fuel",
      "brand": "出光",
      "brand:en": "Idemitsu Kosan",
      "brand:wikidata": "Q2216770",
      "brand:wikipedia": "en:Idemitsu Kosan",
      "name": "出光",
      "name:en": "Idemitsu Kosan"
    }
  },
  "amenity/fuel|台灣中油": {
    "count": 343,
    "countryCodes": ["tw"],
    "match": ["amenity/fuel|中油"],
    "tags": {
      "amenity": "fuel",
      "brand": "台灣中油",
      "brand:en": "CPC Corporation, Taiwan",
      "brand:wikidata": "Q21527177",
      "brand:wikipedia": "en:CPC Corporation",
      "name": "台灣中油",
      "name:en": "CPC Corporation, Taiwan"
    }
  },
  "amenity/fuel|昭和シェル": {
    "count": 348,
    "countryCodes": ["jp"],
    "match": ["amenity/fuel|昭和シェル石油"],
    "tags": {
      "amenity": "fuel",
      "brand": "昭和シェル",
      "brand:en": "Showa Shell Sekiyu",
      "brand:ja": "昭和シェル",
      "brand:wikidata": "Q277115",
      "brand:wikipedia": "en:Showa Shell Sekiyu",
      "name": "昭和シェル",
      "name:en": "Showa Shell Sekiyu",
      "name:ja": "昭和シェル"
    }
  }
}