{
  "amenity/hospital|Select Specialty Hospital": {
    "countryCodes": ["us"],
    "matchNames": ["select speciality"],
    "tags": {
      "amenity": "hospital",
      "brand": "Select Specialty Hospital",
      "brand:wikidata": "Q66360902",
      "healthcare": "hospital",
      "name": "Select Specialty Hospital"
    }
  },
  "amenity/hospital|Shriners Hospital for Children": {
    "countryCodes": ["us"],
    "matchNames": [
      "shriners burn hospital",
      "shriners hospital",
      "shriners hospitals for children"
    ],
    "tags": {
      "amenity": "hospital",
      "brand": "Shriners Hospitals for Children",
      "brand:wikidata": "Q7504109",
      "brand:wikipedia": "en:Shriners Hospitals for Children",
      "emergency": "no",
      "healthcare": "hospital",
      "healthcare:speciality": "paediatrics",
      "name": "Shriners Hospitals for Children"
    }
  },
  "amenity/hospital|VA Medical Center": {
    "countryCodes": ["us"],
    "matchNames": [
      "department of veterans affairs medical center",
      "veterans administration",
      "veterans administration hospital",
      "veterans administration medical center",
      "veterans affairs",
      "veterans affairs hospital",
      "veterans affairs medical center"
    ],
    "tags": {
      "amenity": "hospital",
      "brand": "VA",
      "brand:wikidata": "Q6580225",
      "brand:wikipedia": "en:Veterans Health Administration",
      "healthcare": "hospital",
      "healthcare:for": "veterans",
      "name": "VA Medical Center",
      "short_name": "VA"
    }
  }
}