{
  "amenity/kindergarten|Children's Learning Adventure": {
    "countryCodes": ["us"],
    "tags": {
      "after_school": "yes",
      "amenity": "kindergarten",
      "brand": "Children's Learning Adventure",
      "brand:wikidata": "Q64821213",
      "brand:wikipedia": "en:Children's Learning Adventure",
      "fee": "yes",
      "isced:level": "0",
      "name": "Children's Learning Adventure",
      "nursery": "yes",
      "preschool": "yes",
      "short_name": "CLA"
    }
  },
  "amenity/kindergarten|KinderCare": {
    "countryCodes": ["us"],
    "tags": {
      "after_school": "yes",
      "alt_name": "KinderCare Learning Center",
      "amenity": "kindergarten",
      "brand": "KinderCare",
      "brand:wikidata": "Q6410551",
      "brand:wikipedia": "en:KinderCare Learning Centers",
      "fee": "yes",
      "isced:level": "0",
      "max_age": "12",
      "min_age": "6 weeks",
      "name": "KinderCare",
      "nursery": "yes",
      "preschool": "yes"
    }
  }
}