{
  "amenity/payment_centre|Abitab": {
    "count": 107,
    "countryCodes": ["uy"],
    "tags": {
      "amenity": "payment_centre",
      "brand": "Abitab",
      "brand:wikidata": "Q16488129",
      "brand:wikipedia": "es:Abitab",
      "name": "Abitab"
    }
  },
  "amenity/payment_centre|Rapipago": {
    "count": 94,
    "countryCodes": ["ar"],
    "tags": {
      "amenity": "payment_centre",
      "brand": "Rapipago",
      "brand:wikidata": "Q6100413",
      "brand:wikipedia": "es:Rapipago",
      "name": "Rapipago"
    }
  }
}